[{"id":7533,"kode_terminal":192,"pin":2,"date_time":"2022-03-01 07:55:54","ver":1,"status":0},{"id":7541,"kode_terminal":192,"pin":2,"date_time":"2022-03-01 12:00:51","ver":1,"status":0},{"id":7548,"kode_terminal":192,"pin":2,"date_time":"2022-03-01 15:32:03","ver":1,"status":0},{"id":7564,"kode_terminal":192,"pin":2,"date_time":"2022-03-02 08:02:17","ver":1,"status":0},{"id":7567,"kode_terminal":192,"pin":2,"date_time":"2022-03-02 12:03:02","ver":1,"status":0},{"id":7577,"kode_terminal":192,"pin":2,"date_time":"2022-03-02 15:34:46","ver":1,"status":0},{"id":7591,"kode_terminal":192,"pin":2,"date_time":"2022-03-04 08:00:40","ver":1,"status":0},{"id":7594,"kode_terminal":192,"pin":2,"date_time":"2022-03-04 12:02:12","ver":1,"status":0},{"id":7601,"kode_terminal":192,"pin":2,"date_time":"2022-03-04 15:32:02","ver":1,"status":0},{"id":7619,"kode_terminal":192,"pin":2,"date_time":"2022-03-07 08:09:47","ver":1,"status":0},{"id":7620,"kode_terminal":192,"pin":2,"date_time":"2022-03-07 12:00:36","ver":1,"status":0},{"id":7629,"kode_terminal":192,"pin":2,"date_time":"2022-03-07 15:40:34","ver":1,"status":0},{"id":7647,"kode_terminal":192,"pin":2,"date_time":"2022-03-08 08:05:28","ver":1,"status":0},{"id":7657,"kode_terminal":192,"pin":2,"date_time":"2022-03-08 12:49:47","ver":1,"status":0},{"id":7658,"kode_terminal":192,"pin":2,"date_time":"2022-03-08 15:33:03","ver":1,"status":0},{"id":7676,"kode_terminal":192,"pin":2,"date_time":"2022-03-09 08:06:31","ver":1,"status":0},{"id":7681,"kode_terminal":192,"pin":2,"date_time":"2022-03-09 12:14:29","ver":1,"status":0},{"id":7684,"kode_terminal":192,"pin":2,"date_time":"2022-03-09 15:35:57","ver":1,"status":0},{"id":7703,"kode_terminal":192,"pin":2,"date_time":"2022-03-10 08:08:14","ver":1,"status":0},{"id":7707,"kode_terminal":192,"pin":2,"date_time":"2022-03-10 12:05:49","ver":1,"status":0},{"id":7715,"kode_terminal":192,"pin":2,"date_time":"2022-03-10 15:45:23","ver":1,"status":0},{"id":7730,"kode_terminal":192,"pin":2,"date_time":"2022-03-11 08:07:26","ver":1,"status":0},{"id":7733,"kode_terminal":192,"pin":2,"date_time":"2022-03-11 12:05:01","ver":1,"status":0},{"id":7742,"kode_terminal":192,"pin":2,"date_time":"2022-03-11 15:35:59","ver":1,"status":0},{"id":7756,"kode_terminal":192,"pin":2,"date_time":"2022-03-14 08:05:03","ver":1,"status":0},{"id":7759,"kode_terminal":192,"pin":2,"date_time":"2022-03-14 12:02:13","ver":1,"status":0},{"id":7765,"kode_terminal":192,"pin":2,"date_time":"2022-03-14 15:31:26","ver":1,"status":0},{"id":7784,"kode_terminal":192,"pin":2,"date_time":"2022-03-15 08:06:34","ver":1,"status":0},{"id":7785,"kode_terminal":192,"pin":2,"date_time":"2022-03-15 12:01:26","ver":1,"status":0},{"id":7793,"kode_terminal":192,"pin":2,"date_time":"2022-03-15 15:31:22","ver":1,"status":0},{"id":7807,"kode_terminal":192,"pin":2,"date_time":"2022-03-16 08:09:11","ver":1,"status":0},{"id":7809,"kode_terminal":192,"pin":2,"date_time":"2022-03-16 12:01:22","ver":1,"status":0},{"id":7819,"kode_terminal":192,"pin":2,"date_time":"2022-03-16 15:49:06","ver":1,"status":0},{"id":7833,"kode_terminal":192,"pin":2,"date_time":"2022-03-17 08:05:59","ver":1,"status":0},{"id":7834,"kode_terminal":192,"pin":2,"date_time":"2022-03-17 12:07:53","ver":1,"status":0},{"id":7841,"kode_terminal":192,"pin":2,"date_time":"2022-03-17 15:31:07","ver":1,"status":0},{"id":7855,"kode_terminal":192,"pin":2,"date_time":"2022-03-18 08:09:14","ver":1,"status":0},{"id":7859,"kode_terminal":192,"pin":2,"date_time":"2022-03-18 12:08:07","ver":1,"status":0},{"id":7865,"kode_terminal":192,"pin":2,"date_time":"2022-03-18 16:04:19","ver":1,"status":0},{"id":7878,"kode_terminal":192,"pin":2,"date_time":"2022-03-21 08:08:27","ver":1,"status":0},{"id":7886,"kode_terminal":192,"pin":2,"date_time":"2022-03-21 12:42:04","ver":1,"status":0},{"id":7890,"kode_terminal":192,"pin":2,"date_time":"2022-03-21 15:33:35","ver":1,"status":0},{"id":7910,"kode_terminal":192,"pin":2,"date_time":"2022-03-22 08:09:38","ver":1,"status":0},{"id":7918,"kode_terminal":192,"pin":2,"date_time":"2022-03-22 15:38:23","ver":1,"status":0},{"id":7932,"kode_terminal":192,"pin":2,"date_time":"2022-03-23 08:07:46","ver":1,"status":0},{"id":7939,"kode_terminal":192,"pin":2,"date_time":"2022-03-23 12:20:26","ver":1,"status":0},{"id":7945,"kode_terminal":192,"pin":2,"date_time":"2022-03-23 16:01:47","ver":1,"status":0},{"id":7954,"kode_terminal":192,"pin":2,"date_time":"2022-03-24 08:07:00","ver":1,"status":0},{"id":7956,"kode_terminal":192,"pin":2,"date_time":"2022-03-24 12:01:48","ver":1,"status":0},{"id":7970,"kode_terminal":192,"pin":2,"date_time":"2022-03-24 15:42:56","ver":1,"status":0},{"id":7983,"kode_terminal":192,"pin":2,"date_time":"2022-03-25 08:10:03","ver":1,"status":0},{"id":7989,"kode_terminal":192,"pin":2,"date_time":"2022-03-25 12:23:01","ver":1,"status":0},{"id":7992,"kode_terminal":192,"pin":2,"date_time":"2022-03-25 15:31:09","ver":1,"status":0},{"id":8008,"kode_terminal":192,"pin":2,"date_time":"2022-03-28 08:04:35","ver":1,"status":0},{"id":8009,"kode_terminal":192,"pin":2,"date_time":"2022-03-28 12:06:14","ver":1,"status":0},{"id":8019,"kode_terminal":192,"pin":2,"date_time":"2022-03-28 15:54:44","ver":1,"status":0},{"id":8036,"kode_terminal":192,"pin":2,"date_time":"2022-03-29 08:07:48","ver":1,"status":0},{"id":8045,"kode_terminal":192,"pin":2,"date_time":"2022-03-29 12:20:42","ver":1,"status":0},{"id":8048,"kode_terminal":192,"pin":2,"date_time":"2022-03-29 15:46:56","ver":1,"status":0},{"id":8063,"kode_terminal":192,"pin":2,"date_time":"2022-03-30 08:00:48","ver":1,"status":4},{"id":8068,"kode_terminal":192,"pin":2,"date_time":"2022-03-30 12:01:39","ver":1,"status":4},{"id":8071,"kode_terminal":192,"pin":2,"date_time":"2022-03-30 12:12:03","ver":1,"status":4},{"id":8080,"kode_terminal":192,"pin":2,"date_time":"2022-03-30 15:47:34","ver":1,"status":4},{"id":8096,"kode_terminal":192,"pin":2,"date_time":"2022-03-31 08:07:11","ver":1,"status":4},{"id":8098,"kode_terminal":192,"pin":2,"date_time":"2022-03-31 12:04:38","ver":1,"status":4},{"id":8106,"kode_terminal":192,"pin":2,"date_time":"2022-03-31 15:32:40","ver":1,"status":4},{"id":8113,"kode_terminal":192,"pin":2,"date_time":"2022-03-31 16:04:35","ver":1,"status":4},{"id":7537,"kode_terminal":192,"pin":5,"date_time":"2022-03-01 08:00:08","ver":1,"status":0},{"id":7540,"kode_terminal":192,"pin":5,"date_time":"2022-03-01 12:00:36","ver":1,"status":0},{"id":7556,"kode_terminal":192,"pin":5,"date_time":"2022-03-01 16:18:39","ver":1,"status":0},{"id":7560,"kode_terminal":192,"pin":5,"date_time":"2022-03-02 07:57:23","ver":1,"status":0},{"id":7572,"kode_terminal":192,"pin":5,"date_time":"2022-03-02 12:13:12","ver":1,"status":0},{"id":7584,"kode_terminal":192,"pin":5,"date_time":"2022-03-02 16:45:54","ver":1,"status":0},{"id":7588,"kode_terminal":192,"pin":5,"date_time":"2022-03-04 07:56:49","ver":1,"status":0},{"id":7599,"kode_terminal":192,"pin":5,"date_time":"2022-03-04 12:56:00","ver":1,"status":0},{"id":7609,"kode_terminal":192,"pin":5,"date_time":"2022-03-04 17:03:31","ver":1,"status":0},{"id":7616,"kode_terminal":192,"pin":5,"date_time":"2022-03-07 08:05:56","ver":1,"status":0},{"id":7628,"kode_terminal":192,"pin":5,"date_time":"2022-03-07 12:57:59","ver":1,"status":0},{"id":7631,"kode_terminal":192,"pin":5,"date_time":"2022-03-07 15:44:58","ver":1,"status":0},{"id":7643,"kode_terminal":192,"pin":5,"date_time":"2022-03-08 07:57:10","ver":1,"status":0},{"id":7655,"kode_terminal":192,"pin":5,"date_time":"2022-03-08 12:44:17","ver":1,"status":0},{"id":7664,"kode_terminal":192,"pin":5,"date_time":"2022-03-08 16:41:24","ver":1,"status":0},{"id":7674,"kode_terminal":192,"pin":5,"date_time":"2022-03-09 08:00:25","ver":1,"status":0},{"id":7678,"kode_terminal":192,"pin":5,"date_time":"2022-03-09 12:06:43","ver":1,"status":0},{"id":7690,"kode_terminal":192,"pin":5,"date_time":"2022-03-09 15:59:29","ver":1,"status":0},{"id":7702,"kode_terminal":192,"pin":5,"date_time":"2022-03-10 08:07:11","ver":1,"status":0},{"id":7705,"kode_terminal":192,"pin":5,"date_time":"2022-03-10 12:03:44","ver":1,"status":0},{"id":7719,"kode_terminal":192,"pin":5,"date_time":"2022-03-10 16:11:08","ver":1,"status":0},{"id":7740,"kode_terminal":192,"pin":5,"date_time":"2022-03-11 12:45:39","ver":1,"status":0},{"id":7746,"kode_terminal":192,"pin":5,"date_time":"2022-03-11 16:04:00","ver":1,"status":0},{"id":7754,"kode_terminal":192,"pin":5,"date_time":"2022-03-14 07:58:08","ver":1,"status":0},{"id":7762,"kode_terminal":192,"pin":5,"date_time":"2022-03-14 12:21:01","ver":1,"status":0},{"id":7769,"kode_terminal":192,"pin":5,"date_time":"2022-03-14 16:00:58","ver":1,"status":0},{"id":7775,"kode_terminal":192,"pin":5,"date_time":"2022-03-15 07:49:25","ver":1,"status":0},{"id":7783,"kode_terminal":192,"pin":5,"date_time":"2022-03-15 08:02:07","ver":1,"status":0},{"id":7788,"kode_terminal":192,"pin":5,"date_time":"2022-03-15 12:06:39","ver":1,"status":0},{"id":7795,"kode_terminal":192,"pin":5,"date_time":"2022-03-15 15:37:21","ver":1,"status":0},{"id":7804,"kode_terminal":192,"pin":5,"date_time":"2022-03-16 07:58:24","ver":1,"status":0},{"id":7806,"kode_terminal":192,"pin":5,"date_time":"2022-03-16 08:08:53","ver":1,"status":0},{"id":7816,"kode_terminal":192,"pin":5,"date_time":"2022-03-16 12:06:19","ver":1,"status":0},{"id":7824,"kode_terminal":192,"pin":5,"date_time":"2022-03-16 16:44:25","ver":1,"status":0},{"id":7828,"kode_terminal":192,"pin":5,"date_time":"2022-03-17 07:56:42","ver":1,"status":0},{"id":7835,"kode_terminal":192,"pin":5,"date_time":"2022-03-17 12:08:31","ver":1,"status":0},{"id":7844,"kode_terminal":192,"pin":5,"date_time":"2022-03-17 16:28:07","ver":1,"status":0},{"id":7851,"kode_terminal":192,"pin":5,"date_time":"2022-03-18 07:58:30","ver":1,"status":0},{"id":7853,"kode_terminal":192,"pin":5,"date_time":"2022-03-18 08:02:33","ver":1,"status":0},{"id":7860,"kode_terminal":192,"pin":5,"date_time":"2022-03-18 12:08:19","ver":1,"status":0},{"id":7868,"kode_terminal":192,"pin":5,"date_time":"2022-03-18 16:17:47","ver":1,"status":0},{"id":7879,"kode_terminal":192,"pin":5,"date_time":"2022-03-21 08:10:26","ver":1,"status":0},{"id":7880,"kode_terminal":192,"pin":5,"date_time":"2022-03-21 12:04:55","ver":1,"status":0},{"id":7896,"kode_terminal":192,"pin":5,"date_time":"2022-03-21 16:20:52","ver":1,"status":0},{"id":7904,"kode_terminal":192,"pin":5,"date_time":"2022-03-22 07:58:03","ver":1,"status":0},{"id":7914,"kode_terminal":192,"pin":5,"date_time":"2022-03-22 12:09:49","ver":1,"status":0},{"id":7921,"kode_terminal":192,"pin":5,"date_time":"2022-03-22 15:40:33","ver":1,"status":0},{"id":7929,"kode_terminal":192,"pin":5,"date_time":"2022-03-23 08:00:44","ver":1,"status":0},{"id":7941,"kode_terminal":192,"pin":5,"date_time":"2022-03-23 12:21:47","ver":1,"status":0},{"id":7944,"kode_terminal":192,"pin":5,"date_time":"2022-03-23 16:01:40","ver":1,"status":0},{"id":7959,"kode_terminal":192,"pin":5,"date_time":"2022-03-24 12:17:46","ver":1,"status":0},{"id":7965,"kode_terminal":192,"pin":5,"date_time":"2022-03-24 15:36:16","ver":1,"status":0},{"id":7979,"kode_terminal":192,"pin":5,"date_time":"2022-03-25 08:02:34","ver":1,"status":0},{"id":7990,"kode_terminal":192,"pin":5,"date_time":"2022-03-25 12:51:41","ver":1,"status":0},{"id":7993,"kode_terminal":192,"pin":5,"date_time":"2022-03-25 15:32:37","ver":1,"status":0},{"id":8003,"kode_terminal":192,"pin":5,"date_time":"2022-03-28 07:58:30","ver":1,"status":0},{"id":8007,"kode_terminal":192,"pin":5,"date_time":"2022-03-28 08:01:08","ver":1,"status":0},{"id":8010,"kode_terminal":192,"pin":5,"date_time":"2022-03-28 12:08:42","ver":1,"status":0},{"id":8026,"kode_terminal":192,"pin":5,"date_time":"2022-03-28 16:32:25","ver":1,"status":0},{"id":8037,"kode_terminal":192,"pin":5,"date_time":"2022-03-29 08:09:11","ver":1,"status":0},{"id":8041,"kode_terminal":192,"pin":5,"date_time":"2022-03-29 12:18:52","ver":1,"status":0},{"id":8047,"kode_terminal":192,"pin":5,"date_time":"2022-03-29 15:46:48","ver":1,"status":0},{"id":8061,"kode_terminal":192,"pin":5,"date_time":"2022-03-30 07:56:30","ver":1,"status":4},{"id":8075,"kode_terminal":192,"pin":5,"date_time":"2022-03-30 12:28:48","ver":1,"status":4},{"id":8084,"kode_terminal":192,"pin":5,"date_time":"2022-03-30 15:50:10","ver":1,"status":4},{"id":8089,"kode_terminal":192,"pin":5,"date_time":"2022-03-31 07:59:02","ver":1,"status":4},{"id":8105,"kode_terminal":192,"pin":5,"date_time":"2022-03-31 12:46:55","ver":1,"status":4},{"id":8109,"kode_terminal":192,"pin":5,"date_time":"2022-03-31 15:35:36","ver":1,"status":4},{"id":7536,"kode_terminal":192,"pin":6,"date_time":"2022-03-01 07:58:36","ver":1,"status":0},{"id":7543,"kode_terminal":192,"pin":6,"date_time":"2022-03-01 12:10:13","ver":1,"status":0},{"id":7553,"kode_terminal":192,"pin":6,"date_time":"2022-03-01 15:50:31","ver":1,"status":0},{"id":7565,"kode_terminal":192,"pin":6,"date_time":"2022-03-02 08:02:52","ver":1,"status":0},{"id":7571,"kode_terminal":192,"pin":6,"date_time":"2022-03-02 12:12:51","ver":1,"status":0},{"id":7574,"kode_terminal":192,"pin":6,"date_time":"2022-03-02 12:30:21","ver":1,"status":0},{"id":7579,"kode_terminal":192,"pin":6,"date_time":"2022-03-02 15:42:28","ver":1,"status":0},{"id":7586,"kode_terminal":192,"pin":6,"date_time":"2022-03-04 07:56:18","ver":1,"status":0},{"id":7596,"kode_terminal":192,"pin":6,"date_time":"2022-03-04 12:07:00","ver":1,"status":0},{"id":7603,"kode_terminal":192,"pin":6,"date_time":"2022-03-04 16:07:07","ver":1,"status":0},{"id":7615,"kode_terminal":192,"pin":6,"date_time":"2022-03-07 07:57:24","ver":1,"status":0},{"id":7623,"kode_terminal":192,"pin":6,"date_time":"2022-03-07 12:12:52","ver":1,"status":0},{"id":7633,"kode_terminal":192,"pin":6,"date_time":"2022-03-07 15:48:28","ver":1,"status":0},{"id":7640,"kode_terminal":192,"pin":6,"date_time":"2022-03-08 07:56:24","ver":1,"status":0},{"id":7649,"kode_terminal":192,"pin":6,"date_time":"2022-03-08 12:14:31","ver":1,"status":0},{"id":7659,"kode_terminal":192,"pin":6,"date_time":"2022-03-08 15:54:55","ver":1,"status":0},{"id":7667,"kode_terminal":192,"pin":6,"date_time":"2022-03-08 17:09:34","ver":1,"status":0},{"id":7675,"kode_terminal":192,"pin":6,"date_time":"2022-03-09 08:04:58","ver":1,"status":0},{"id":7685,"kode_terminal":192,"pin":6,"date_time":"2022-03-09 15:37:03","ver":1,"status":0},{"id":7696,"kode_terminal":192,"pin":6,"date_time":"2022-03-10 07:59:11","ver":1,"status":0},{"id":7704,"kode_terminal":192,"pin":6,"date_time":"2022-03-10 12:03:32","ver":1,"status":0},{"id":7716,"kode_terminal":192,"pin":6,"date_time":"2022-03-10 15:45:41","ver":1,"status":0},{"id":7727,"kode_terminal":192,"pin":6,"date_time":"2022-03-11 07:57:25","ver":1,"status":0},{"id":7735,"kode_terminal":192,"pin":6,"date_time":"2022-03-11 12:08:50","ver":1,"status":0},{"id":7745,"kode_terminal":192,"pin":6,"date_time":"2022-03-11 15:57:35","ver":1,"status":0},{"id":7751,"kode_terminal":192,"pin":6,"date_time":"2022-03-14 07:56:11","ver":1,"status":0},{"id":7761,"kode_terminal":192,"pin":6,"date_time":"2022-03-14 12:14:14","ver":1,"status":0},{"id":7768,"kode_terminal":192,"pin":6,"date_time":"2022-03-14 16:00:42","ver":1,"status":0},{"id":7778,"kode_terminal":192,"pin":6,"date_time":"2022-03-15 07:56:24","ver":1,"status":0},{"id":7786,"kode_terminal":192,"pin":6,"date_time":"2022-03-15 12:04:25","ver":1,"status":0},{"id":7792,"kode_terminal":192,"pin":6,"date_time":"2022-03-15 12:26:52","ver":1,"status":0},{"id":7796,"kode_terminal":192,"pin":6,"date_time":"2022-03-15 15:43:13","ver":1,"status":0},{"id":7800,"kode_terminal":192,"pin":6,"date_time":"2022-03-16 07:56:34","ver":1,"status":0},{"id":7810,"kode_terminal":192,"pin":6,"date_time":"2022-03-16 12:03:50","ver":1,"status":0},{"id":7825,"kode_terminal":192,"pin":6,"date_time":"2022-03-16 16:44:32","ver":1,"status":0},{"id":7830,"kode_terminal":192,"pin":6,"date_time":"2022-03-17 08:01:04","ver":1,"status":0},{"id":7837,"kode_terminal":192,"pin":6,"date_time":"2022-03-17 12:09:01","ver":1,"status":0},{"id":7848,"kode_terminal":192,"pin":6,"date_time":"2022-03-17 17:06:32","ver":1,"status":0},{"id":7854,"kode_terminal":192,"pin":6,"date_time":"2022-03-18 08:02:44","ver":1,"status":0},{"id":7863,"kode_terminal":192,"pin":6,"date_time":"2022-03-18 12:16:18","ver":1,"status":0},{"id":7867,"kode_terminal":192,"pin":6,"date_time":"2022-03-18 16:13:43","ver":1,"status":0},{"id":7874,"kode_terminal":192,"pin":6,"date_time":"2022-03-21 07:58:23","ver":1,"status":0},{"id":7881,"kode_terminal":192,"pin":6,"date_time":"2022-03-21 12:13:26","ver":1,"status":0},{"id":7894,"kode_terminal":192,"pin":6,"date_time":"2022-03-21 15:54:45","ver":1,"status":0},{"id":7907,"kode_terminal":192,"pin":6,"date_time":"2022-03-22 08:03:16","ver":1,"status":0},{"id":7912,"kode_terminal":192,"pin":6,"date_time":"2022-03-22 12:01:47","ver":1,"status":0},{"id":7919,"kode_terminal":192,"pin":6,"date_time":"2022-03-22 15:38:40","ver":1,"status":0},{"id":7924,"kode_terminal":192,"pin":6,"date_time":"2022-03-22 16:06:59","ver":1,"status":0},{"id":7950,"kode_terminal":192,"pin":6,"date_time":"2022-03-24 07:57:28","ver":1,"status":0},{"id":7957,"kode_terminal":192,"pin":6,"date_time":"2022-03-24 12:04:58","ver":1,"status":0},{"id":7968,"kode_terminal":192,"pin":6,"date_time":"2022-03-24 15:38:05","ver":1,"status":0},{"id":7977,"kode_terminal":192,"pin":6,"date_time":"2022-03-25 07:59:01","ver":1,"status":0},{"id":7984,"kode_terminal":192,"pin":6,"date_time":"2022-03-25 12:01:18","ver":1,"status":0},{"id":7994,"kode_terminal":192,"pin":6,"date_time":"2022-03-25 15:36:02","ver":1,"status":0},{"id":8000,"kode_terminal":192,"pin":6,"date_time":"2022-03-28 07:56:12","ver":1,"status":0},{"id":8012,"kode_terminal":192,"pin":6,"date_time":"2022-03-28 12:14:04","ver":1,"status":0},{"id":8024,"kode_terminal":192,"pin":6,"date_time":"2022-03-28 16:00:08","ver":1,"status":0},{"id":8033,"kode_terminal":192,"pin":6,"date_time":"2022-03-29 08:01:13","ver":1,"status":0},{"id":8042,"kode_terminal":192,"pin":6,"date_time":"2022-03-29 12:19:06","ver":1,"status":0},{"id":8054,"kode_terminal":192,"pin":6,"date_time":"2022-03-29 15:56:30","ver":1,"status":0},{"id":8060,"kode_terminal":192,"pin":6,"date_time":"2022-03-30 07:56:16","ver":1,"status":4},{"id":8070,"kode_terminal":192,"pin":6,"date_time":"2022-03-30 12:11:48","ver":1,"status":4},{"id":8082,"kode_terminal":192,"pin":6,"date_time":"2022-03-30 15:48:25","ver":1,"status":4},{"id":8092,"kode_terminal":192,"pin":6,"date_time":"2022-03-31 08:03:40","ver":1,"status":4},{"id":8102,"kode_terminal":192,"pin":6,"date_time":"2022-03-31 12:10:38","ver":1,"status":4},{"id":8108,"kode_terminal":192,"pin":6,"date_time":"2022-03-31 15:35:24","ver":1,"status":4},{"id":7535,"kode_terminal":192,"pin":7,"date_time":"2022-03-01 07:58:28","ver":1,"status":0},{"id":7546,"kode_terminal":192,"pin":7,"date_time":"2022-03-01 12:29:26","ver":1,"status":0},{"id":7550,"kode_terminal":192,"pin":7,"date_time":"2022-03-01 15:47:55","ver":1,"status":0},{"id":7554,"kode_terminal":192,"pin":7,"date_time":"2022-03-01 16:03:29","ver":1,"status":0},{"id":7561,"kode_terminal":192,"pin":7,"date_time":"2022-03-02 07:57:39","ver":1,"status":0},{"id":7569,"kode_terminal":192,"pin":7,"date_time":"2022-03-02 12:09:11","ver":1,"status":0},{"id":7575,"kode_terminal":192,"pin":7,"date_time":"2022-03-02 12:33:54","ver":1,"status":0},{"id":7582,"kode_terminal":192,"pin":7,"date_time":"2022-03-02 15:55:33","ver":1,"status":0},{"id":7590,"kode_terminal":192,"pin":7,"date_time":"2022-03-04 07:59:08","ver":1,"status":0},{"id":7598,"kode_terminal":192,"pin":7,"date_time":"2022-03-04 12:11:27","ver":1,"status":0},{"id":7604,"kode_terminal":192,"pin":7,"date_time":"2022-03-04 16:07:16","ver":1,"status":0},{"id":7606,"kode_terminal":192,"pin":7,"date_time":"2022-03-04 16:14:44","ver":1,"status":0},{"id":7613,"kode_terminal":192,"pin":7,"date_time":"2022-03-07 07:56:41","ver":1,"status":0},{"id":7624,"kode_terminal":192,"pin":7,"date_time":"2022-03-07 12:20:33","ver":1,"status":0},{"id":7630,"kode_terminal":192,"pin":7,"date_time":"2022-03-07 15:41:17","ver":1,"status":0},{"id":7634,"kode_terminal":192,"pin":7,"date_time":"2022-03-07 15:51:32","ver":1,"status":0},{"id":7645,"kode_terminal":192,"pin":7,"date_time":"2022-03-08 08:03:36","ver":1,"status":0},{"id":7646,"kode_terminal":192,"pin":7,"date_time":"2022-03-08 08:05:10","ver":1,"status":0},{"id":7650,"kode_terminal":192,"pin":7,"date_time":"2022-03-08 12:14:43","ver":1,"status":0},{"id":7660,"kode_terminal":192,"pin":7,"date_time":"2022-03-08 16:01:41","ver":1,"status":0},{"id":7671,"kode_terminal":192,"pin":7,"date_time":"2022-03-09 07:58:01","ver":1,"status":0},{"id":7677,"kode_terminal":192,"pin":7,"date_time":"2022-03-09 12:06:32","ver":1,"status":0},{"id":7686,"kode_terminal":192,"pin":7,"date_time":"2022-03-09 15:37:13","ver":1,"status":0},{"id":7688,"kode_terminal":192,"pin":7,"date_time":"2022-03-09 15:57:23","ver":1,"status":0},{"id":7695,"kode_terminal":192,"pin":7,"date_time":"2022-03-10 07:57:34","ver":1,"status":0},{"id":7698,"kode_terminal":192,"pin":7,"date_time":"2022-03-10 08:00:55","ver":1,"status":0},{"id":7708,"kode_terminal":192,"pin":7,"date_time":"2022-03-10 12:06:25","ver":1,"status":0},{"id":7712,"kode_terminal":192,"pin":7,"date_time":"2022-03-10 12:33:09","ver":1,"status":0},{"id":7717,"kode_terminal":192,"pin":7,"date_time":"2022-03-10 15:45:53","ver":1,"status":0},{"id":7726,"kode_terminal":192,"pin":7,"date_time":"2022-03-11 07:57:16","ver":1,"status":0},{"id":7729,"kode_terminal":192,"pin":7,"date_time":"2022-03-11 08:07:21","ver":1,"status":0},{"id":7736,"kode_terminal":192,"pin":7,"date_time":"2022-03-11 12:09:00","ver":1,"status":0},{"id":7737,"kode_terminal":192,"pin":7,"date_time":"2022-03-11 12:12:21","ver":1,"status":0},{"id":7743,"kode_terminal":192,"pin":7,"date_time":"2022-03-11 15:36:23","ver":1,"status":0},{"id":7752,"kode_terminal":192,"pin":7,"date_time":"2022-03-14 07:57:24","ver":1,"status":0},{"id":7760,"kode_terminal":192,"pin":7,"date_time":"2022-03-14 12:07:55","ver":1,"status":0},{"id":7767,"kode_terminal":192,"pin":7,"date_time":"2022-03-14 15:48:24","ver":1,"status":0},{"id":7772,"kode_terminal":192,"pin":7,"date_time":"2022-03-14 16:24:54","ver":1,"status":0},{"id":7780,"kode_terminal":192,"pin":7,"date_time":"2022-03-15 07:59:34","ver":1,"status":0},{"id":7787,"kode_terminal":192,"pin":7,"date_time":"2022-03-15 12:04:38","ver":1,"status":0},{"id":7791,"kode_terminal":192,"pin":7,"date_time":"2022-03-15 12:26:44","ver":1,"status":0},{"id":7797,"kode_terminal":192,"pin":7,"date_time":"2022-03-15 15:43:23","ver":1,"status":0},{"id":7803,"kode_terminal":192,"pin":7,"date_time":"2022-03-16 07:57:53","ver":1,"status":0},{"id":7812,"kode_terminal":192,"pin":7,"date_time":"2022-03-16 12:04:34","ver":1,"status":0},{"id":7814,"kode_terminal":192,"pin":7,"date_time":"2022-03-16 12:06:03","ver":1,"status":0},{"id":7820,"kode_terminal":192,"pin":7,"date_time":"2022-03-16 15:56:28","ver":1,"status":0},{"id":7839,"kode_terminal":192,"pin":7,"date_time":"2022-03-17 12:32:46","ver":1,"status":0},{"id":7840,"kode_terminal":192,"pin":7,"date_time":"2022-03-17 12:44:15","ver":1,"status":0},{"id":7843,"kode_terminal":192,"pin":7,"date_time":"2022-03-17 15:56:12","ver":1,"status":0},{"id":7845,"kode_terminal":192,"pin":7,"date_time":"2022-03-17 16:28:16","ver":1,"status":0},{"id":7850,"kode_terminal":192,"pin":7,"date_time":"2022-03-18 07:58:18","ver":1,"status":0},{"id":7861,"kode_terminal":192,"pin":7,"date_time":"2022-03-18 12:08:28","ver":1,"status":0},{"id":7866,"kode_terminal":192,"pin":7,"date_time":"2022-03-18 16:13:28","ver":1,"status":0},{"id":7873,"kode_terminal":192,"pin":7,"date_time":"2022-03-21 07:57:53","ver":1,"status":0},{"id":7884,"kode_terminal":192,"pin":7,"date_time":"2022-03-21 12:29:25","ver":1,"status":0},{"id":7891,"kode_terminal":192,"pin":7,"date_time":"2022-03-21 15:35:57","ver":1,"status":0},{"id":7905,"kode_terminal":192,"pin":7,"date_time":"2022-03-22 08:01:50","ver":1,"status":0},{"id":7913,"kode_terminal":192,"pin":7,"date_time":"2022-03-22 12:06:22","ver":1,"status":0},{"id":7915,"kode_terminal":192,"pin":7,"date_time":"2022-03-22 12:27:57","ver":1,"status":0},{"id":7920,"kode_terminal":192,"pin":7,"date_time":"2022-03-22 15:38:55","ver":1,"status":0},{"id":7927,"kode_terminal":192,"pin":7,"date_time":"2022-03-23 07:58:40","ver":1,"status":0},{"id":7934,"kode_terminal":192,"pin":7,"date_time":"2022-03-23 12:08:04","ver":1,"status":0},{"id":7942,"kode_terminal":192,"pin":7,"date_time":"2022-03-23 15:43:53","ver":1,"status":0},{"id":7951,"kode_terminal":192,"pin":7,"date_time":"2022-03-24 07:58:08","ver":1,"status":0},{"id":7962,"kode_terminal":192,"pin":7,"date_time":"2022-03-24 12:23:04","ver":1,"status":0},{"id":7969,"kode_terminal":192,"pin":7,"date_time":"2022-03-24 15:41:17","ver":1,"status":0},{"id":7972,"kode_terminal":192,"pin":7,"date_time":"2022-03-24 15:55:19","ver":1,"status":0},{"id":7981,"kode_terminal":192,"pin":7,"date_time":"2022-03-25 08:02:52","ver":1,"status":0},{"id":7985,"kode_terminal":192,"pin":7,"date_time":"2022-03-25 12:06:46","ver":1,"status":0},{"id":7996,"kode_terminal":192,"pin":7,"date_time":"2022-03-25 15:37:10","ver":1,"status":0},{"id":7997,"kode_terminal":192,"pin":7,"date_time":"2022-03-25 16:04:19","ver":1,"status":0},{"id":8002,"kode_terminal":192,"pin":7,"date_time":"2022-03-28 07:56:48","ver":1,"status":0},{"id":8013,"kode_terminal":192,"pin":7,"date_time":"2022-03-28 12:18:19","ver":1,"status":0},{"id":8021,"kode_terminal":192,"pin":7,"date_time":"2022-03-28 15:55:26","ver":1,"status":0},{"id":8023,"kode_terminal":192,"pin":7,"date_time":"2022-03-28 15:58:18","ver":1,"status":0},{"id":8031,"kode_terminal":192,"pin":7,"date_time":"2022-03-29 07:57:08","ver":1,"status":0},{"id":8039,"kode_terminal":192,"pin":7,"date_time":"2022-03-29 12:14:25","ver":1,"status":0},{"id":8050,"kode_terminal":192,"pin":7,"date_time":"2022-03-29 15:53:28","ver":1,"status":0},{"id":8057,"kode_terminal":192,"pin":7,"date_time":"2022-03-29 16:10:35","ver":1,"status":0},{"id":8062,"kode_terminal":192,"pin":7,"date_time":"2022-03-30 07:59:07","ver":1,"status":4},{"id":8076,"kode_terminal":192,"pin":7,"date_time":"2022-03-30 12:29:13","ver":1,"status":4},{"id":8077,"kode_terminal":192,"pin":7,"date_time":"2022-03-30 12:33:21","ver":1,"status":4},{"id":8083,"kode_terminal":192,"pin":7,"date_time":"2022-03-30 15:48:36","ver":1,"status":4},{"id":8090,"kode_terminal":192,"pin":7,"date_time":"2022-03-31 07:59:13","ver":1,"status":4},{"id":8097,"kode_terminal":192,"pin":7,"date_time":"2022-03-31 12:04:26","ver":1,"status":4},{"id":8110,"kode_terminal":192,"pin":7,"date_time":"2022-03-31 15:44:19","ver":1,"status":4},{"id":7538,"kode_terminal":192,"pin":8,"date_time":"2022-03-01 08:03:22","ver":1,"status":0},{"id":7544,"kode_terminal":192,"pin":8,"date_time":"2022-03-01 12:27:01","ver":1,"status":0},{"id":7549,"kode_terminal":192,"pin":8,"date_time":"2022-03-01 15:45:15","ver":1,"status":0},{"id":7562,"kode_terminal":192,"pin":8,"date_time":"2022-03-02 07:59:50","ver":1,"status":0},{"id":7570,"kode_terminal":192,"pin":8,"date_time":"2022-03-02 12:12:26","ver":1,"status":0},{"id":7583,"kode_terminal":192,"pin":8,"date_time":"2022-03-02 16:34:48","ver":1,"status":0},{"id":7589,"kode_terminal":192,"pin":8,"date_time":"2022-03-04 07:58:26","ver":1,"status":0},{"id":7593,"kode_terminal":192,"pin":8,"date_time":"2022-03-04 12:01:49","ver":1,"status":0},{"id":7608,"kode_terminal":192,"pin":8,"date_time":"2022-03-04 16:22:42","ver":1,"status":0},{"id":7617,"kode_terminal":192,"pin":8,"date_time":"2022-03-07 08:06:36","ver":1,"status":0},{"id":7626,"kode_terminal":192,"pin":8,"date_time":"2022-03-07 12:24:13","ver":1,"status":0},{"id":7637,"kode_terminal":192,"pin":8,"date_time":"2022-03-07 16:26:30","ver":1,"status":0},{"id":7648,"kode_terminal":192,"pin":8,"date_time":"2022-03-08 08:06:10","ver":1,"status":0},{"id":7654,"kode_terminal":192,"pin":8,"date_time":"2022-03-08 12:24:01","ver":1,"status":0},{"id":7663,"kode_terminal":192,"pin":8,"date_time":"2022-03-08 16:39:51","ver":1,"status":0},{"id":7672,"kode_terminal":192,"pin":8,"date_time":"2022-03-09 07:58:21","ver":1,"status":0},{"id":7683,"kode_terminal":192,"pin":8,"date_time":"2022-03-09 12:25:35","ver":1,"status":0},{"id":7693,"kode_terminal":192,"pin":8,"date_time":"2022-03-09 17:11:14","ver":1,"status":0},{"id":7697,"kode_terminal":192,"pin":8,"date_time":"2022-03-10 07:59:37","ver":1,"status":0},{"id":7710,"kode_terminal":192,"pin":8,"date_time":"2022-03-10 12:10:50","ver":1,"status":0},{"id":7720,"kode_terminal":192,"pin":8,"date_time":"2022-03-10 16:38:12","ver":1,"status":0},{"id":7724,"kode_terminal":192,"pin":8,"date_time":"2022-03-11 07:56:53","ver":1,"status":0},{"id":7738,"kode_terminal":192,"pin":8,"date_time":"2022-03-11 12:18:49","ver":1,"status":0},{"id":7744,"kode_terminal":192,"pin":8,"date_time":"2022-03-11 15:54:56","ver":1,"status":0},{"id":7757,"kode_terminal":192,"pin":8,"date_time":"2022-03-14 08:11:46","ver":1,"status":0},{"id":7764,"kode_terminal":192,"pin":8,"date_time":"2022-03-14 12:31:48","ver":1,"status":0},{"id":7773,"kode_terminal":192,"pin":8,"date_time":"2022-03-14 16:44:29","ver":1,"status":0},{"id":7777,"kode_terminal":192,"pin":8,"date_time":"2022-03-15 07:56:13","ver":1,"status":0},{"id":7808,"kode_terminal":192,"pin":8,"date_time":"2022-03-16 08:10:04","ver":1,"status":0},{"id":7813,"kode_terminal":192,"pin":8,"date_time":"2022-03-16 12:05:55","ver":1,"status":0},{"id":7818,"kode_terminal":192,"pin":8,"date_time":"2022-03-16 15:48:03","ver":1,"status":0},{"id":7847,"kode_terminal":192,"pin":8,"date_time":"2022-03-17 16:48:06","ver":1,"status":0},{"id":7852,"kode_terminal":192,"pin":8,"date_time":"2022-03-18 08:02:04","ver":1,"status":0},{"id":7858,"kode_terminal":192,"pin":8,"date_time":"2022-03-18 12:07:57","ver":1,"status":0},{"id":7870,"kode_terminal":192,"pin":8,"date_time":"2022-03-18 16:28:08","ver":1,"status":0},{"id":7871,"kode_terminal":192,"pin":8,"date_time":"2022-03-21 07:56:27","ver":1,"status":0},{"id":7883,"kode_terminal":192,"pin":8,"date_time":"2022-03-21 12:20:04","ver":1,"status":0},{"id":7899,"kode_terminal":192,"pin":8,"date_time":"2022-03-21 17:02:50","ver":1,"status":0},{"id":7908,"kode_terminal":192,"pin":8,"date_time":"2022-03-22 08:03:29","ver":1,"status":0},{"id":7916,"kode_terminal":192,"pin":8,"date_time":"2022-03-22 12:28:10","ver":1,"status":0},{"id":7926,"kode_terminal":192,"pin":8,"date_time":"2022-03-22 16:50:03","ver":1,"status":0},{"id":7948,"kode_terminal":192,"pin":8,"date_time":"2022-03-23 17:10:50","ver":1,"status":0},{"id":7973,"kode_terminal":192,"pin":8,"date_time":"2022-03-24 16:11:54","ver":1,"status":0},{"id":7978,"kode_terminal":192,"pin":8,"date_time":"2022-03-25 08:02:12","ver":1,"status":0},{"id":8005,"kode_terminal":192,"pin":8,"date_time":"2022-03-28 08:00:39","ver":1,"status":0},{"id":8015,"kode_terminal":192,"pin":8,"date_time":"2022-03-28 12:29:07","ver":1,"status":0},{"id":8025,"kode_terminal":192,"pin":8,"date_time":"2022-03-28 16:14:36","ver":1,"status":0},{"id":8035,"kode_terminal":192,"pin":8,"date_time":"2022-03-29 08:03:40","ver":1,"status":0},{"id":8046,"kode_terminal":192,"pin":8,"date_time":"2022-03-29 12:28:31","ver":1,"status":0},{"id":8058,"kode_terminal":192,"pin":8,"date_time":"2022-03-29 16:46:57","ver":1,"status":0},{"id":8064,"kode_terminal":192,"pin":8,"date_time":"2022-03-30 08:03:04","ver":1,"status":4},{"id":8074,"kode_terminal":192,"pin":8,"date_time":"2022-03-30 12:28:01","ver":1,"status":4},{"id":8086,"kode_terminal":192,"pin":8,"date_time":"2022-03-30 16:49:17","ver":1,"status":4},{"id":8095,"kode_terminal":192,"pin":8,"date_time":"2022-03-31 08:06:56","ver":1,"status":4},{"id":8104,"kode_terminal":192,"pin":8,"date_time":"2022-03-31 12:26:14","ver":1,"status":4},{"id":8114,"kode_terminal":192,"pin":8,"date_time":"2022-03-31 16:04:48","ver":1,"status":4},{"id":7539,"kode_terminal":192,"pin":9,"date_time":"2022-03-01 08:10:20","ver":1,"status":0},{"id":7545,"kode_terminal":192,"pin":9,"date_time":"2022-03-01 12:27:26","ver":1,"status":0},{"id":7552,"kode_terminal":192,"pin":9,"date_time":"2022-03-01 15:50:06","ver":1,"status":0},{"id":7557,"kode_terminal":192,"pin":9,"date_time":"2022-03-01 17:57:27","ver":1,"status":0},{"id":7563,"kode_terminal":192,"pin":9,"date_time":"2022-03-02 08:00:24","ver":1,"status":0},{"id":7573,"kode_terminal":192,"pin":9,"date_time":"2022-03-02 12:30:11","ver":1,"status":0},{"id":7581,"kode_terminal":192,"pin":9,"date_time":"2022-03-02 15:54:49","ver":1,"status":0},{"id":7587,"kode_terminal":192,"pin":9,"date_time":"2022-03-04 07:56:32","ver":1,"status":0},{"id":7595,"kode_terminal":192,"pin":9,"date_time":"2022-03-04 12:04:26","ver":1,"status":0},{"id":7610,"kode_terminal":192,"pin":9,"date_time":"2022-03-04 17:03:44","ver":1,"status":0},{"id":7618,"kode_terminal":192,"pin":9,"date_time":"2022-03-07 08:08:54","ver":1,"status":0},{"id":7625,"kode_terminal":192,"pin":9,"date_time":"2022-03-07 12:23:20","ver":1,"status":0},{"id":7636,"kode_terminal":192,"pin":9,"date_time":"2022-03-07 16:21:53","ver":1,"status":0},{"id":7644,"kode_terminal":192,"pin":9,"date_time":"2022-03-08 07:57:17","ver":1,"status":0},{"id":7652,"kode_terminal":192,"pin":9,"date_time":"2022-03-08 12:15:12","ver":1,"status":0},{"id":7666,"kode_terminal":192,"pin":9,"date_time":"2022-03-08 16:43:44","ver":1,"status":0},{"id":7670,"kode_terminal":192,"pin":9,"date_time":"2022-03-09 07:56:34","ver":1,"status":0},{"id":7682,"kode_terminal":192,"pin":9,"date_time":"2022-03-09 12:25:29","ver":1,"status":0},{"id":7687,"kode_terminal":192,"pin":9,"date_time":"2022-03-09 15:46:13","ver":1,"status":0},{"id":7700,"kode_terminal":192,"pin":9,"date_time":"2022-03-10 08:01:48","ver":1,"status":0},{"id":7711,"kode_terminal":192,"pin":9,"date_time":"2022-03-10 12:19:54","ver":1,"status":0},{"id":7718,"kode_terminal":192,"pin":9,"date_time":"2022-03-10 16:00:13","ver":1,"status":0},{"id":7725,"kode_terminal":192,"pin":9,"date_time":"2022-03-11 07:57:04","ver":1,"status":0},{"id":7734,"kode_terminal":192,"pin":9,"date_time":"2022-03-11 12:05:52","ver":1,"status":0},{"id":7748,"kode_terminal":192,"pin":9,"date_time":"2022-03-11 16:42:57","ver":1,"status":0},{"id":7755,"kode_terminal":192,"pin":9,"date_time":"2022-03-14 08:04:55","ver":1,"status":0},{"id":7763,"kode_terminal":192,"pin":9,"date_time":"2022-03-14 12:22:29","ver":1,"status":0},{"id":7771,"kode_terminal":192,"pin":9,"date_time":"2022-03-14 16:20:02","ver":1,"status":0},{"id":7782,"kode_terminal":192,"pin":9,"date_time":"2022-03-15 08:01:59","ver":1,"status":0},{"id":7790,"kode_terminal":192,"pin":9,"date_time":"2022-03-15 12:26:28","ver":1,"status":0},{"id":7799,"kode_terminal":192,"pin":9,"date_time":"2022-03-15 16:44:07","ver":1,"status":0},{"id":7805,"kode_terminal":192,"pin":9,"date_time":"2022-03-16 07:59:53","ver":1,"status":0},{"id":7815,"kode_terminal":192,"pin":9,"date_time":"2022-03-16 12:06:11","ver":1,"status":0},{"id":7823,"kode_terminal":192,"pin":9,"date_time":"2022-03-16 16:32:00","ver":1,"status":0},{"id":7826,"kode_terminal":192,"pin":9,"date_time":"2022-03-16 16:44:41","ver":1,"status":0},{"id":7831,"kode_terminal":192,"pin":9,"date_time":"2022-03-17 08:01:41","ver":1,"status":0},{"id":7832,"kode_terminal":192,"pin":9,"date_time":"2022-03-17 08:03:04","ver":1,"status":0},{"id":7838,"kode_terminal":192,"pin":9,"date_time":"2022-03-17 12:25:33","ver":1,"status":0},{"id":7846,"kode_terminal":192,"pin":9,"date_time":"2022-03-17 16:33:47","ver":1,"status":0},{"id":7849,"kode_terminal":192,"pin":9,"date_time":"2022-03-18 07:57:25","ver":1,"status":0},{"id":7862,"kode_terminal":192,"pin":9,"date_time":"2022-03-18 12:09:09","ver":1,"status":0},{"id":7869,"kode_terminal":192,"pin":9,"date_time":"2022-03-18 16:19:46","ver":1,"status":0},{"id":7877,"kode_terminal":192,"pin":9,"date_time":"2022-03-21 08:07:49","ver":1,"status":0},{"id":7885,"kode_terminal":192,"pin":9,"date_time":"2022-03-21 12:29:34","ver":1,"status":0},{"id":7888,"kode_terminal":192,"pin":9,"date_time":"2022-03-21 12:47:40","ver":1,"status":0},{"id":7892,"kode_terminal":192,"pin":9,"date_time":"2022-03-21 15:53:05","ver":1,"status":0},{"id":7895,"kode_terminal":192,"pin":9,"date_time":"2022-03-21 16:04:00","ver":1,"status":0},{"id":7909,"kode_terminal":192,"pin":9,"date_time":"2022-03-22 08:04:50","ver":1,"status":0},{"id":7925,"kode_terminal":192,"pin":9,"date_time":"2022-03-22 16:49:56","ver":1,"status":0},{"id":7931,"kode_terminal":192,"pin":9,"date_time":"2022-03-23 08:07:39","ver":1,"status":0},{"id":7937,"kode_terminal":192,"pin":9,"date_time":"2022-03-23 12:15:31","ver":1,"status":0},{"id":7938,"kode_terminal":192,"pin":9,"date_time":"2022-03-23 12:19:07","ver":1,"status":0},{"id":7960,"kode_terminal":192,"pin":9,"date_time":"2022-03-24 12:21:16","ver":1,"status":0},{"id":7971,"kode_terminal":192,"pin":9,"date_time":"2022-03-24 15:51:44","ver":1,"status":0},{"id":7974,"kode_terminal":192,"pin":9,"date_time":"2022-03-24 17:23:40","ver":1,"status":0},{"id":7976,"kode_terminal":192,"pin":9,"date_time":"2022-03-25 07:58:52","ver":1,"status":0},{"id":7988,"kode_terminal":192,"pin":9,"date_time":"2022-03-25 12:22:51","ver":1,"status":0},{"id":8016,"kode_terminal":192,"pin":9,"date_time":"2022-03-28 12:31:34","ver":1,"status":0},{"id":8028,"kode_terminal":192,"pin":9,"date_time":"2022-03-28 17:21:50","ver":1,"status":0},{"id":8034,"kode_terminal":192,"pin":9,"date_time":"2022-03-29 08:01:49","ver":1,"status":0},{"id":8044,"kode_terminal":192,"pin":9,"date_time":"2022-03-29 12:20:30","ver":1,"status":0},{"id":8051,"kode_terminal":192,"pin":9,"date_time":"2022-03-29 15:54:14","ver":1,"status":0},{"id":8053,"kode_terminal":192,"pin":9,"date_time":"2022-03-29 15:55:58","ver":1,"status":0},{"id":8055,"kode_terminal":192,"pin":9,"date_time":"2022-03-29 16:00:45","ver":1,"status":0},{"id":8065,"kode_terminal":192,"pin":9,"date_time":"2022-03-30 08:03:29","ver":1,"status":4},{"id":8078,"kode_terminal":192,"pin":9,"date_time":"2022-03-30 12:43:02","ver":1,"status":4},{"id":8087,"kode_terminal":192,"pin":9,"date_time":"2022-03-30 16:49:42","ver":1,"status":4},{"id":8093,"kode_terminal":192,"pin":9,"date_time":"2022-03-31 08:04:23","ver":1,"status":4},{"id":8099,"kode_terminal":192,"pin":9,"date_time":"2022-03-31 12:04:50","ver":1,"status":4},{"id":8115,"kode_terminal":192,"pin":9,"date_time":"2022-03-31 17:09:10","ver":1,"status":4},{"id":7611,"kode_terminal":192,"pin":10,"date_time":"2022-03-07 07:37:56","ver":1,"status":0},{"id":7621,"kode_terminal":192,"pin":10,"date_time":"2022-03-07 12:04:13","ver":1,"status":0},{"id":7638,"kode_terminal":192,"pin":10,"date_time":"2022-03-07 17:06:40","ver":1,"status":0},{"id":7641,"kode_terminal":192,"pin":10,"date_time":"2022-03-08 07:56:38","ver":1,"status":0},{"id":7653,"kode_terminal":192,"pin":10,"date_time":"2022-03-08 12:15:31","ver":1,"status":0},{"id":7662,"kode_terminal":192,"pin":10,"date_time":"2022-03-08 16:02:06","ver":1,"status":0},{"id":7668,"kode_terminal":192,"pin":10,"date_time":"2022-03-09 07:29:06","ver":1,"status":0},{"id":7679,"kode_terminal":192,"pin":10,"date_time":"2022-03-09 12:07:23","ver":1,"status":0},{"id":7691,"kode_terminal":192,"pin":10,"date_time":"2022-03-09 16:19:09","ver":1,"status":0},{"id":7701,"kode_terminal":192,"pin":10,"date_time":"2022-03-10 08:05:57","ver":1,"status":0},{"id":7706,"kode_terminal":192,"pin":10,"date_time":"2022-03-10 12:05:41","ver":1,"status":0},{"id":7721,"kode_terminal":192,"pin":10,"date_time":"2022-03-10 16:42:10","ver":1,"status":0},{"id":7731,"kode_terminal":192,"pin":10,"date_time":"2022-03-11 08:14:20","ver":1,"status":0},{"id":7732,"kode_terminal":192,"pin":10,"date_time":"2022-03-11 12:04:43","ver":1,"status":0},{"id":7749,"kode_terminal":192,"pin":10,"date_time":"2022-03-11 16:43:14","ver":1,"status":0},{"id":7876,"kode_terminal":192,"pin":10,"date_time":"2022-03-21 08:03:44","ver":1,"status":0},{"id":7882,"kode_terminal":192,"pin":10,"date_time":"2022-03-21 12:15:37","ver":1,"status":0},{"id":7897,"kode_terminal":192,"pin":10,"date_time":"2022-03-21 16:38:42","ver":1,"status":0},{"id":7898,"kode_terminal":192,"pin":10,"date_time":"2022-03-21 16:40:12","ver":1,"status":0},{"id":7903,"kode_terminal":192,"pin":10,"date_time":"2022-03-22 07:56:50","ver":1,"status":0},{"id":7906,"kode_terminal":192,"pin":10,"date_time":"2022-03-22 08:02:08","ver":1,"status":0},{"id":7930,"kode_terminal":192,"pin":10,"date_time":"2022-03-23 08:05:37","ver":1,"status":0},{"id":7936,"kode_terminal":192,"pin":10,"date_time":"2022-03-23 12:08:38","ver":1,"status":0},{"id":7946,"kode_terminal":192,"pin":10,"date_time":"2022-03-23 16:02:16","ver":1,"status":0},{"id":7952,"kode_terminal":192,"pin":10,"date_time":"2022-03-24 07:58:32","ver":1,"status":0},{"id":7953,"kode_terminal":192,"pin":10,"date_time":"2022-03-24 08:03:26","ver":1,"status":0},{"id":7958,"kode_terminal":192,"pin":10,"date_time":"2022-03-24 12:05:26","ver":1,"status":0},{"id":7967,"kode_terminal":192,"pin":10,"date_time":"2022-03-24 15:37:04","ver":1,"status":0},{"id":7982,"kode_terminal":192,"pin":10,"date_time":"2022-03-25 08:02:58","ver":1,"status":0},{"id":7986,"kode_terminal":192,"pin":10,"date_time":"2022-03-25 12:08:55","ver":1,"status":0},{"id":7999,"kode_terminal":192,"pin":10,"date_time":"2022-03-25 16:35:12","ver":1,"status":0},{"id":8004,"kode_terminal":192,"pin":10,"date_time":"2022-03-28 07:59:51","ver":1,"status":0},{"id":8011,"kode_terminal":192,"pin":10,"date_time":"2022-03-28 12:09:22","ver":1,"status":0},{"id":8020,"kode_terminal":192,"pin":10,"date_time":"2022-03-28 15:54:59","ver":1,"status":0},{"id":8022,"kode_terminal":192,"pin":10,"date_time":"2022-03-28 15:56:29","ver":1,"status":0},{"id":8032,"kode_terminal":192,"pin":10,"date_time":"2022-03-29 08:01:03","ver":1,"status":0},{"id":8038,"kode_terminal":192,"pin":10,"date_time":"2022-03-29 12:02:00","ver":1,"status":0},{"id":8052,"kode_terminal":192,"pin":10,"date_time":"2022-03-29 15:54:25","ver":1,"status":0},{"id":8066,"kode_terminal":192,"pin":10,"date_time":"2022-03-30 08:04:15","ver":1,"status":4},{"id":8069,"kode_terminal":192,"pin":10,"date_time":"2022-03-30 12:05:35","ver":1,"status":4},{"id":8079,"kode_terminal":192,"pin":10,"date_time":"2022-03-30 15:47:22","ver":1,"status":4},{"id":8094,"kode_terminal":192,"pin":10,"date_time":"2022-03-31 08:05:48","ver":1,"status":4},{"id":8100,"kode_terminal":192,"pin":10,"date_time":"2022-03-31 12:06:31","ver":1,"status":4},{"id":8107,"kode_terminal":192,"pin":10,"date_time":"2022-03-31 15:33:14","ver":1,"status":4},{"id":7534,"kode_terminal":192,"pin":11,"date_time":"2022-03-01 07:56:16","ver":1,"status":0},{"id":7542,"kode_terminal":192,"pin":11,"date_time":"2022-03-01 12:05:13","ver":1,"status":0},{"id":7551,"kode_terminal":192,"pin":11,"date_time":"2022-03-01 15:49:56","ver":1,"status":0},{"id":7558,"kode_terminal":192,"pin":11,"date_time":"2022-03-02 07:50:54","ver":1,"status":0},{"id":7566,"kode_terminal":192,"pin":11,"date_time":"2022-03-02 08:03:08","ver":1,"status":0},{"id":7568,"kode_terminal":192,"pin":11,"date_time":"2022-03-02 12:08:33","ver":1,"status":0},{"id":7580,"kode_terminal":192,"pin":11,"date_time":"2022-03-02 15:43:31","ver":1,"status":0},{"id":7585,"kode_terminal":192,"pin":11,"date_time":"2022-03-04 07:56:02","ver":1,"status":0},{"id":7597,"kode_terminal":192,"pin":11,"date_time":"2022-03-04 12:11:14","ver":1,"status":0},{"id":7602,"kode_terminal":192,"pin":11,"date_time":"2022-03-04 15:58:56","ver":1,"status":0},{"id":7605,"kode_terminal":192,"pin":11,"date_time":"2022-03-04 16:07:27","ver":1,"status":0},{"id":7612,"kode_terminal":192,"pin":11,"date_time":"2022-03-07 07:56:34","ver":1,"status":0},{"id":7622,"kode_terminal":192,"pin":11,"date_time":"2022-03-07 12:12:40","ver":1,"status":0},{"id":7632,"kode_terminal":192,"pin":11,"date_time":"2022-03-07 15:47:20","ver":1,"status":0},{"id":7642,"kode_terminal":192,"pin":11,"date_time":"2022-03-08 07:56:57","ver":1,"status":0},{"id":7651,"kode_terminal":192,"pin":11,"date_time":"2022-03-08 12:15:02","ver":1,"status":0},{"id":7661,"kode_terminal":192,"pin":11,"date_time":"2022-03-08 16:01:51","ver":1,"status":0},{"id":7673,"kode_terminal":192,"pin":11,"date_time":"2022-03-09 07:58:52","ver":1,"status":0},{"id":7680,"kode_terminal":192,"pin":11,"date_time":"2022-03-09 12:07:39","ver":1,"status":0},{"id":7689,"kode_terminal":192,"pin":11,"date_time":"2022-03-09 15:59:18","ver":1,"status":0},{"id":7699,"kode_terminal":192,"pin":11,"date_time":"2022-03-10 08:01:42","ver":1,"status":0},{"id":7709,"kode_terminal":192,"pin":11,"date_time":"2022-03-10 12:08:18","ver":1,"status":0},{"id":7714,"kode_terminal":192,"pin":11,"date_time":"2022-03-10 15:45:07","ver":1,"status":0},{"id":7728,"kode_terminal":192,"pin":11,"date_time":"2022-03-11 07:57:51","ver":1,"status":0},{"id":7739,"kode_terminal":192,"pin":11,"date_time":"2022-03-11 12:25:39","ver":1,"status":0},{"id":7753,"kode_terminal":192,"pin":11,"date_time":"2022-03-14 07:57:56","ver":1,"status":0},{"id":7758,"kode_terminal":192,"pin":11,"date_time":"2022-03-14 12:01:55","ver":1,"status":0},{"id":7766,"kode_terminal":192,"pin":11,"date_time":"2022-03-14 15:32:02","ver":1,"status":0},{"id":7774,"kode_terminal":192,"pin":11,"date_time":"2022-03-15 07:43:51","ver":1,"status":0},{"id":7779,"kode_terminal":192,"pin":11,"date_time":"2022-03-15 07:57:01","ver":1,"status":0},{"id":7781,"kode_terminal":192,"pin":11,"date_time":"2022-03-15 07:59:41","ver":1,"status":0},{"id":7794,"kode_terminal":192,"pin":11,"date_time":"2022-03-15 15:31:40","ver":1,"status":0},{"id":7802,"kode_terminal":192,"pin":11,"date_time":"2022-03-16 07:57:25","ver":1,"status":0},{"id":7811,"kode_terminal":192,"pin":11,"date_time":"2022-03-16 12:04:23","ver":1,"status":0},{"id":7821,"kode_terminal":192,"pin":11,"date_time":"2022-03-16 15:57:20","ver":1,"status":0},{"id":7829,"kode_terminal":192,"pin":11,"date_time":"2022-03-17 07:57:21","ver":1,"status":0},{"id":7836,"kode_terminal":192,"pin":11,"date_time":"2022-03-17 12:08:45","ver":1,"status":0},{"id":7842,"kode_terminal":192,"pin":11,"date_time":"2022-03-17 15:55:50","ver":1,"status":0},{"id":7856,"kode_terminal":192,"pin":11,"date_time":"2022-03-18 08:16:15","ver":1,"status":0},{"id":7857,"kode_terminal":192,"pin":11,"date_time":"2022-03-18 12:01:41","ver":1,"status":0},{"id":7864,"kode_terminal":192,"pin":11,"date_time":"2022-03-18 16:00:30","ver":1,"status":0},{"id":7875,"kode_terminal":192,"pin":11,"date_time":"2022-03-21 08:02:18","ver":1,"status":0},{"id":7889,"kode_terminal":192,"pin":11,"date_time":"2022-03-21 12:49:01","ver":1,"status":0},{"id":7893,"kode_terminal":192,"pin":11,"date_time":"2022-03-21 15:53:23","ver":1,"status":0},{"id":7902,"kode_terminal":192,"pin":11,"date_time":"2022-03-22 07:56:37","ver":1,"status":0},{"id":7911,"kode_terminal":192,"pin":11,"date_time":"2022-03-22 12:01:26","ver":1,"status":0},{"id":7922,"kode_terminal":192,"pin":11,"date_time":"2022-03-22 15:47:50","ver":1,"status":0},{"id":7933,"kode_terminal":192,"pin":11,"date_time":"2022-03-23 08:24:43","ver":1,"status":0},{"id":7935,"kode_terminal":192,"pin":11,"date_time":"2022-03-23 12:08:16","ver":1,"status":0},{"id":7943,"kode_terminal":192,"pin":11,"date_time":"2022-03-23 15:54:23","ver":1,"status":0},{"id":7955,"kode_terminal":192,"pin":11,"date_time":"2022-03-24 08:11:58","ver":1,"status":0},{"id":7961,"kode_terminal":192,"pin":11,"date_time":"2022-03-24 12:22:55","ver":1,"status":0},{"id":7964,"kode_terminal":192,"pin":11,"date_time":"2022-03-24 15:31:41","ver":1,"status":0},{"id":7980,"kode_terminal":192,"pin":11,"date_time":"2022-03-25 08:02:43","ver":1,"status":0},{"id":7987,"kode_terminal":192,"pin":11,"date_time":"2022-03-25 12:12:30","ver":1,"status":0},{"id":7995,"kode_terminal":192,"pin":11,"date_time":"2022-03-25 15:36:25","ver":1,"status":0},{"id":8006,"kode_terminal":192,"pin":11,"date_time":"2022-03-28 08:00:51","ver":1,"status":0},{"id":8014,"kode_terminal":192,"pin":11,"date_time":"2022-03-28 12:20:14","ver":1,"status":0},{"id":8018,"kode_terminal":192,"pin":11,"date_time":"2022-03-28 15:53:50","ver":1,"status":0},{"id":8030,"kode_terminal":192,"pin":11,"date_time":"2022-03-29 07:56:13","ver":1,"status":0},{"id":8040,"kode_terminal":192,"pin":11,"date_time":"2022-03-29 12:15:29","ver":1,"status":0},{"id":8049,"kode_terminal":192,"pin":11,"date_time":"2022-03-29 15:53:04","ver":1,"status":0},{"id":8067,"kode_terminal":192,"pin":11,"date_time":"2022-03-30 08:04:58","ver":1,"status":4},{"id":8072,"kode_terminal":192,"pin":11,"date_time":"2022-03-30 12:13:57","ver":1,"status":4},{"id":8081,"kode_terminal":192,"pin":11,"date_time":"2022-03-30 15:48:02","ver":1,"status":4},{"id":8091,"kode_terminal":192,"pin":11,"date_time":"2022-03-31 08:02:54","ver":1,"status":4},{"id":8101,"kode_terminal":192,"pin":11,"date_time":"2022-03-31 12:10:14","ver":1,"status":4},{"id":8111,"kode_terminal":192,"pin":11,"date_time":"2022-03-31 15:48:38","ver":1,"status":4},{"id":7532,"kode_terminal":192,"pin":12,"date_time":"2022-03-01 07:55:45","ver":1,"status":0},{"id":7547,"kode_terminal":192,"pin":12,"date_time":"2022-03-01 12:35:08","ver":1,"status":0},{"id":7555,"kode_terminal":192,"pin":12,"date_time":"2022-03-01 16:16:54","ver":1,"status":0},{"id":7559,"kode_terminal":192,"pin":12,"date_time":"2022-03-02 07:55:38","ver":1,"status":0},{"id":7576,"kode_terminal":192,"pin":12,"date_time":"2022-03-02 12:36:46","ver":1,"status":0},{"id":7578,"kode_terminal":192,"pin":12,"date_time":"2022-03-02 15:37:46","ver":1,"status":0},{"id":7592,"kode_terminal":192,"pin":12,"date_time":"2022-03-04 08:01:01","ver":1,"status":0},{"id":7600,"kode_terminal":192,"pin":12,"date_time":"2022-03-04 12:58:12","ver":1,"status":0},{"id":7607,"kode_terminal":192,"pin":12,"date_time":"2022-03-04 16:15:24","ver":1,"status":0},{"id":7614,"kode_terminal":192,"pin":12,"date_time":"2022-03-07 07:56:56","ver":1,"status":0},{"id":7627,"kode_terminal":192,"pin":12,"date_time":"2022-03-07 12:45:28","ver":1,"status":0},{"id":7635,"kode_terminal":192,"pin":12,"date_time":"2022-03-07 16:21:09","ver":1,"status":0},{"id":7639,"kode_terminal":192,"pin":12,"date_time":"2022-03-08 07:55:04","ver":1,"status":0},{"id":7656,"kode_terminal":192,"pin":12,"date_time":"2022-03-08 12:49:39","ver":1,"status":0},{"id":7665,"kode_terminal":192,"pin":12,"date_time":"2022-03-08 16:41:55","ver":1,"status":0},{"id":7669,"kode_terminal":192,"pin":12,"date_time":"2022-03-09 07:55:40","ver":1,"status":0},{"id":7692,"kode_terminal":192,"pin":12,"date_time":"2022-03-09 16:38:03","ver":1,"status":0},{"id":7694,"kode_terminal":192,"pin":12,"date_time":"2022-03-10 07:55:18","ver":1,"status":0},{"id":7713,"kode_terminal":192,"pin":12,"date_time":"2022-03-10 12:43:21","ver":1,"status":0},{"id":7722,"kode_terminal":192,"pin":12,"date_time":"2022-03-10 16:44:18","ver":1,"status":0},{"id":7723,"kode_terminal":192,"pin":12,"date_time":"2022-03-11 07:55:12","ver":1,"status":0},{"id":7741,"kode_terminal":192,"pin":12,"date_time":"2022-03-11 13:07:08","ver":1,"status":0},{"id":7747,"kode_terminal":192,"pin":12,"date_time":"2022-03-11 16:19:36","ver":1,"status":0},{"id":7750,"kode_terminal":192,"pin":12,"date_time":"2022-03-14 07:55:14","ver":1,"status":0},{"id":7770,"kode_terminal":192,"pin":12,"date_time":"2022-03-14 16:03:48","ver":1,"status":0},{"id":7776,"kode_terminal":192,"pin":12,"date_time":"2022-03-15 07:56:02","ver":1,"status":0},{"id":7789,"kode_terminal":192,"pin":12,"date_time":"2022-03-15 12:26:18","ver":1,"status":0},{"id":7798,"kode_terminal":192,"pin":12,"date_time":"2022-03-15 15:55:11","ver":1,"status":0},{"id":7801,"kode_terminal":192,"pin":12,"date_time":"2022-03-16 07:56:49","ver":1,"status":0},{"id":7817,"kode_terminal":192,"pin":12,"date_time":"2022-03-16 12:44:36","ver":1,"status":0},{"id":7822,"kode_terminal":192,"pin":12,"date_time":"2022-03-16 16:00:07","ver":1,"status":0},{"id":7827,"kode_terminal":192,"pin":12,"date_time":"2022-03-17 07:56:02","ver":1,"status":0},{"id":7872,"kode_terminal":192,"pin":12,"date_time":"2022-03-21 07:57:45","ver":1,"status":0},{"id":7887,"kode_terminal":192,"pin":12,"date_time":"2022-03-21 12:47:27","ver":1,"status":0},{"id":7900,"kode_terminal":192,"pin":12,"date_time":"2022-03-21 17:03:54","ver":1,"status":0},{"id":7901,"kode_terminal":192,"pin":12,"date_time":"2022-03-22 07:55:13","ver":1,"status":0},{"id":7917,"kode_terminal":192,"pin":12,"date_time":"2022-03-22 12:49:15","ver":1,"status":0},{"id":7923,"kode_terminal":192,"pin":12,"date_time":"2022-03-22 15:57:45","ver":1,"status":0},{"id":7928,"kode_terminal":192,"pin":12,"date_time":"2022-03-23 08:00:22","ver":1,"status":0},{"id":7940,"kode_terminal":192,"pin":12,"date_time":"2022-03-23 12:21:37","ver":1,"status":0},{"id":7947,"kode_terminal":192,"pin":12,"date_time":"2022-03-23 16:02:38","ver":1,"status":0},{"id":7949,"kode_terminal":192,"pin":12,"date_time":"2022-03-24 07:55:26","ver":1,"status":0},{"id":7963,"kode_terminal":192,"pin":12,"date_time":"2022-03-24 12:49:51","ver":1,"status":0},{"id":7966,"kode_terminal":192,"pin":12,"date_time":"2022-03-24 15:36:25","ver":1,"status":0},{"id":7975,"kode_terminal":192,"pin":12,"date_time":"2022-03-25 07:55:28","ver":1,"status":0},{"id":7991,"kode_terminal":192,"pin":12,"date_time":"2022-03-25 12:53:13","ver":1,"status":0},{"id":7998,"kode_terminal":192,"pin":12,"date_time":"2022-03-25 16:07:55","ver":1,"status":0},{"id":8001,"kode_terminal":192,"pin":12,"date_time":"2022-03-28 07:56:28","ver":1,"status":0},{"id":8017,"kode_terminal":192,"pin":12,"date_time":"2022-03-28 12:47:18","ver":1,"status":0},{"id":8027,"kode_terminal":192,"pin":12,"date_time":"2022-03-28 16:38:05","ver":1,"status":0},{"id":8029,"kode_terminal":192,"pin":12,"date_time":"2022-03-29 07:56:04","ver":1,"status":0},{"id":8043,"kode_terminal":192,"pin":12,"date_time":"2022-03-29 12:19:37","ver":1,"status":0},{"id":8056,"kode_terminal":192,"pin":12,"date_time":"2022-03-29 16:01:01","ver":1,"status":0},{"id":8059,"kode_terminal":192,"pin":12,"date_time":"2022-03-30 07:55:08","ver":1,"status":4},{"id":8073,"kode_terminal":192,"pin":12,"date_time":"2022-03-30 12:14:14","ver":1,"status":4},{"id":8085,"kode_terminal":192,"pin":12,"date_time":"2022-03-30 15:52:11","ver":1,"status":4},{"id":8088,"kode_terminal":192,"pin":12,"date_time":"2022-03-31 07:57:46","ver":1,"status":4},{"id":8103,"kode_terminal":192,"pin":12,"date_time":"2022-03-31 12:17:34","ver":1,"status":4},{"id":8112,"kode_terminal":192,"pin":12,"date_time":"2022-03-31 16:03:48","ver":1,"status":4}]