[{"id":1134,"kode_terminal":154,"pin":4,"date_time":"2022-02-02 07:00:02","ver":1,"status":0},{"id":1135,"kode_terminal":154,"pin":13,"date_time":"2022-02-02 07:03:30","ver":1,"status":0},{"id":1136,"kode_terminal":154,"pin":2,"date_time":"2022-02-02 07:04:21","ver":1,"status":0},{"id":1137,"kode_terminal":154,"pin":22,"date_time":"2022-02-02 07:33:59","ver":1,"status":0},{"id":1138,"kode_terminal":154,"pin":17,"date_time":"2022-02-02 07:51:33","ver":1,"status":0},{"id":1139,"kode_terminal":154,"pin":17,"date_time":"2022-02-02 07:58:07","ver":1,"status":0},{"id":1140,"kode_terminal":154,"pin":19,"date_time":"2022-02-02 08:11:43","ver":1,"status":0},{"id":1141,"kode_terminal":154,"pin":14,"date_time":"2022-02-02 08:14:41","ver":1,"status":0},{"id":1142,"kode_terminal":154,"pin":20,"date_time":"2022-02-02 08:28:38","ver":1,"status":0},{"id":1143,"kode_terminal":154,"pin":18,"date_time":"2022-02-02 08:57:19","ver":1,"status":0},{"id":1144,"kode_terminal":154,"pin":15,"date_time":"2022-02-02 08:58:21","ver":1,"status":0},{"id":1145,"kode_terminal":154,"pin":22,"date_time":"2022-02-02 12:01:39","ver":1,"status":0},{"id":1146,"kode_terminal":154,"pin":14,"date_time":"2022-02-02 12:03:14","ver":1,"status":0},{"id":1147,"kode_terminal":154,"pin":17,"date_time":"2022-02-02 12:03:30","ver":1,"status":0},{"id":1148,"kode_terminal":154,"pin":4,"date_time":"2022-02-02 12:03:41","ver":1,"status":0},{"id":1149,"kode_terminal":154,"pin":17,"date_time":"2022-02-02 12:05:24","ver":1,"status":0},{"id":1150,"kode_terminal":154,"pin":18,"date_time":"2022-02-02 12:08:31","ver":1,"status":0},{"id":1151,"kode_terminal":154,"pin":13,"date_time":"2022-02-02 12:11:37","ver":1,"status":0},{"id":1152,"kode_terminal":154,"pin":2,"date_time":"2022-02-02 12:21:23","ver":1,"status":0},{"id":1153,"kode_terminal":154,"pin":15,"date_time":"2022-02-02 12:42:35","ver":1,"status":0},{"id":1154,"kode_terminal":154,"pin":20,"date_time":"2022-02-02 13:09:38","ver":1,"status":0},{"id":1155,"kode_terminal":154,"pin":18,"date_time":"2022-02-02 16:00:14","ver":1,"status":1},{"id":1156,"kode_terminal":154,"pin":17,"date_time":"2022-02-02 16:00:26","ver":1,"status":1},{"id":1157,"kode_terminal":154,"pin":22,"date_time":"2022-02-02 16:03:45","ver":1,"status":1},{"id":1158,"kode_terminal":154,"pin":13,"date_time":"2022-02-02 16:05:19","ver":1,"status":1},{"id":1159,"kode_terminal":154,"pin":14,"date_time":"2022-02-02 16:05:49","ver":1,"status":1},{"id":1160,"kode_terminal":154,"pin":15,"date_time":"2022-02-02 16:21:10","ver":1,"status":1},{"id":1161,"kode_terminal":154,"pin":4,"date_time":"2022-02-02 16:28:10","ver":1,"status":1},{"id":1162,"kode_terminal":154,"pin":19,"date_time":"2022-02-02 16:30:39","ver":1,"status":1},{"id":1163,"kode_terminal":154,"pin":2,"date_time":"2022-02-02 17:37:23","ver":1,"status":1},{"id":1164,"kode_terminal":154,"pin":4,"date_time":"2022-02-03 07:00:30","ver":1,"status":0},{"id":1165,"kode_terminal":154,"pin":18,"date_time":"2022-02-03 07:00:45","ver":1,"status":0},{"id":1166,"kode_terminal":154,"pin":22,"date_time":"2022-02-03 07:38:11","ver":1,"status":0},{"id":1167,"kode_terminal":154,"pin":14,"date_time":"2022-02-03 07:44:09","ver":1,"status":0},{"id":1168,"kode_terminal":154,"pin":19,"date_time":"2022-02-03 07:55:53","ver":1,"status":0},{"id":1169,"kode_terminal":154,"pin":17,"date_time":"2022-02-03 07:58:02","ver":1,"status":0},{"id":1170,"kode_terminal":154,"pin":20,"date_time":"2022-02-03 08:26:44","ver":1,"status":0},{"id":1171,"kode_terminal":154,"pin":13,"date_time":"2022-02-03 08:36:33","ver":1,"status":0},{"id":1172,"kode_terminal":154,"pin":2,"date_time":"2022-02-03 10:59:46","ver":1,"status":0},{"id":1173,"kode_terminal":154,"pin":17,"date_time":"2022-02-03 12:00:20","ver":1,"status":0},{"id":1174,"kode_terminal":154,"pin":18,"date_time":"2022-02-03 12:00:35","ver":1,"status":0},{"id":1175,"kode_terminal":154,"pin":13,"date_time":"2022-02-03 12:03:50","ver":1,"status":0},{"id":1176,"kode_terminal":154,"pin":22,"date_time":"2022-02-03 12:07:49","ver":1,"status":0},{"id":1177,"kode_terminal":154,"pin":4,"date_time":"2022-02-03 12:09:26","ver":1,"status":0},{"id":1178,"kode_terminal":154,"pin":2,"date_time":"2022-02-03 12:12:56","ver":1,"status":0},{"id":1179,"kode_terminal":154,"pin":17,"date_time":"2022-02-03 12:13:55","ver":1,"status":0},{"id":1180,"kode_terminal":154,"pin":2,"date_time":"2022-02-03 12:14:17","ver":1,"status":0},{"id":1181,"kode_terminal":154,"pin":20,"date_time":"2022-02-03 12:33:14","ver":1,"status":0},{"id":1182,"kode_terminal":154,"pin":4,"date_time":"2022-02-03 16:00:31","ver":1,"status":0},{"id":1183,"kode_terminal":154,"pin":17,"date_time":"2022-02-03 16:00:45","ver":1,"status":0},{"id":1184,"kode_terminal":154,"pin":22,"date_time":"2022-02-03 16:03:14","ver":1,"status":0},{"id":1185,"kode_terminal":154,"pin":13,"date_time":"2022-02-03 16:16:50","ver":1,"status":0},{"id":1186,"kode_terminal":154,"pin":18,"date_time":"2022-02-03 17:34:30","ver":1,"status":1},{"id":1187,"kode_terminal":154,"pin":2,"date_time":"2022-02-03 18:13:02","ver":1,"status":1},{"id":1188,"kode_terminal":154,"pin":4,"date_time":"2022-02-04 07:11:23","ver":1,"status":0},{"id":1189,"kode_terminal":154,"pin":2,"date_time":"2022-02-04 07:11:38","ver":1,"status":0},{"id":1190,"kode_terminal":154,"pin":22,"date_time":"2022-02-04 07:13:14","ver":1,"status":0},{"id":1191,"kode_terminal":154,"pin":18,"date_time":"2022-02-04 07:33:58","ver":1,"status":0},{"id":1192,"kode_terminal":154,"pin":17,"date_time":"2022-02-04 08:06:47","ver":1,"status":0},{"id":1193,"kode_terminal":154,"pin":19,"date_time":"2022-02-04 08:45:28","ver":1,"status":0},{"id":1194,"kode_terminal":154,"pin":13,"date_time":"2022-02-04 08:51:42","ver":1,"status":0},{"id":1195,"kode_terminal":154,"pin":15,"date_time":"2022-02-04 10:33:23","ver":1,"status":0},{"id":1196,"kode_terminal":154,"pin":18,"date_time":"2022-02-04 12:00:25","ver":1,"status":0},{"id":1197,"kode_terminal":154,"pin":17,"date_time":"2022-02-04 12:00:51","ver":1,"status":0},{"id":1198,"kode_terminal":154,"pin":15,"date_time":"2022-02-04 12:01:15","ver":1,"status":0},{"id":1199,"kode_terminal":154,"pin":4,"date_time":"2022-02-04 12:02:34","ver":1,"status":0},{"id":1200,"kode_terminal":154,"pin":13,"date_time":"2022-02-04 12:02:43","ver":1,"status":0},{"id":1201,"kode_terminal":154,"pin":22,"date_time":"2022-02-04 12:09:05","ver":1,"status":0},{"id":1202,"kode_terminal":154,"pin":19,"date_time":"2022-02-04 12:32:50","ver":1,"status":0},{"id":1203,"kode_terminal":154,"pin":2,"date_time":"2022-02-04 12:34:25","ver":1,"status":0},{"id":1204,"kode_terminal":154,"pin":15,"date_time":"2022-02-04 16:30:55","ver":1,"status":0},{"id":1205,"kode_terminal":154,"pin":18,"date_time":"2022-02-04 16:31:07","ver":1,"status":0},{"id":1206,"kode_terminal":154,"pin":13,"date_time":"2022-02-04 16:31:44","ver":1,"status":0},{"id":1207,"kode_terminal":154,"pin":4,"date_time":"2022-02-04 16:33:16","ver":1,"status":0},{"id":1208,"kode_terminal":154,"pin":22,"date_time":"2022-02-04 16:33:30","ver":1,"status":0},{"id":1209,"kode_terminal":154,"pin":2,"date_time":"2022-02-04 16:42:21","ver":1,"status":0},{"id":1210,"kode_terminal":154,"pin":19,"date_time":"2022-02-04 16:58:41","ver":1,"status":0},{"id":1211,"kode_terminal":154,"pin":17,"date_time":"2022-02-04 17:00:42","ver":1,"status":0},{"id":1212,"kode_terminal":154,"pin":4,"date_time":"2022-02-07 07:00:03","ver":1,"status":0},{"id":1213,"kode_terminal":154,"pin":18,"date_time":"2022-02-07 07:10:43","ver":1,"status":0},{"id":1214,"kode_terminal":154,"pin":22,"date_time":"2022-02-07 07:12:02","ver":1,"status":0},{"id":1215,"kode_terminal":154,"pin":14,"date_time":"2022-02-07 07:36:19","ver":1,"status":0},{"id":1216,"kode_terminal":154,"pin":19,"date_time":"2022-02-07 07:55:10","ver":1,"status":0},{"id":1217,"kode_terminal":154,"pin":17,"date_time":"2022-02-07 08:04:14","ver":1,"status":0},{"id":1218,"kode_terminal":154,"pin":13,"date_time":"2022-02-07 11:41:30","ver":1,"status":0},{"id":1219,"kode_terminal":154,"pin":2,"date_time":"2022-02-07 11:46:26","ver":1,"status":0},{"id":1220,"kode_terminal":154,"pin":4,"date_time":"2022-02-07 12:00:37","ver":1,"status":0},{"id":1221,"kode_terminal":154,"pin":13,"date_time":"2022-02-07 12:00:45","ver":1,"status":0},{"id":1222,"kode_terminal":154,"pin":18,"date_time":"2022-02-07 12:00:54","ver":1,"status":0},{"id":1223,"kode_terminal":154,"pin":2,"date_time":"2022-02-07 12:12:14","ver":1,"status":0},{"id":1224,"kode_terminal":154,"pin":19,"date_time":"2022-02-07 12:15:27","ver":1,"status":0},{"id":1225,"kode_terminal":154,"pin":17,"date_time":"2022-02-07 12:27:45","ver":1,"status":0},{"id":1226,"kode_terminal":154,"pin":22,"date_time":"2022-02-07 12:28:28","ver":1,"status":0},{"id":1227,"kode_terminal":154,"pin":18,"date_time":"2022-02-07 16:00:40","ver":1,"status":1},{"id":1228,"kode_terminal":154,"pin":4,"date_time":"2022-02-07 16:00:57","ver":1,"status":1},{"id":1229,"kode_terminal":154,"pin":17,"date_time":"2022-02-07 16:01:09","ver":1,"status":1},{"id":1230,"kode_terminal":154,"pin":13,"date_time":"2022-02-07 16:01:28","ver":1,"status":1},{"id":1231,"kode_terminal":154,"pin":22,"date_time":"2022-02-07 16:02:49","ver":1,"status":1},{"id":1232,"kode_terminal":154,"pin":19,"date_time":"2022-02-07 16:44:31","ver":1,"status":1},{"id":1233,"kode_terminal":154,"pin":2,"date_time":"2022-02-07 16:47:11","ver":1,"status":1},{"id":1234,"kode_terminal":154,"pin":4,"date_time":"2022-02-08 07:01:13","ver":1,"status":0},{"id":1235,"kode_terminal":154,"pin":18,"date_time":"2022-02-08 07:06:57","ver":1,"status":0},{"id":1236,"kode_terminal":154,"pin":22,"date_time":"2022-02-08 07:27:59","ver":1,"status":0},{"id":1237,"kode_terminal":154,"pin":17,"date_time":"2022-02-08 07:38:21","ver":1,"status":0},{"id":1238,"kode_terminal":154,"pin":14,"date_time":"2022-02-08 07:43:53","ver":1,"status":0},{"id":1239,"kode_terminal":154,"pin":2,"date_time":"2022-02-08 07:51:33","ver":1,"status":0},{"id":1240,"kode_terminal":154,"pin":19,"date_time":"2022-02-08 08:02:37","ver":1,"status":0},{"id":1241,"kode_terminal":154,"pin":13,"date_time":"2022-02-08 09:16:13","ver":1,"status":0},{"id":1242,"kode_terminal":154,"pin":20,"date_time":"2022-02-08 09:16:39","ver":1,"status":0},{"id":1243,"kode_terminal":154,"pin":15,"date_time":"2022-02-08 13:06:45","ver":1,"status":0},{"id":1244,"kode_terminal":154,"pin":14,"date_time":"2022-02-08 13:06:59","ver":1,"status":0},{"id":1245,"kode_terminal":154,"pin":4,"date_time":"2022-02-09 07:02:07","ver":1,"status":0},{"id":1246,"kode_terminal":154,"pin":2,"date_time":"2022-02-09 07:20:51","ver":1,"status":0},{"id":1247,"kode_terminal":154,"pin":14,"date_time":"2022-02-09 07:21:04","ver":1,"status":0},{"id":1248,"kode_terminal":154,"pin":22,"date_time":"2022-02-09 07:34:51","ver":1,"status":0},{"id":1249,"kode_terminal":154,"pin":18,"date_time":"2022-02-09 07:38:45","ver":1,"status":0},{"id":1250,"kode_terminal":154,"pin":17,"date_time":"2022-02-09 08:00:45","ver":1,"status":0},{"id":1251,"kode_terminal":154,"pin":19,"date_time":"2022-02-09 08:55:10","ver":1,"status":0},{"id":1252,"kode_terminal":154,"pin":13,"date_time":"2022-02-09 09:18:12","ver":1,"status":0},{"id":1253,"kode_terminal":154,"pin":15,"date_time":"2022-02-09 10:57:40","ver":1,"status":0},{"id":1254,"kode_terminal":154,"pin":13,"date_time":"2022-02-09 11:50:10","ver":1,"status":0},{"id":1255,"kode_terminal":154,"pin":13,"date_time":"2022-02-09 12:00:13","ver":1,"status":0},{"id":1256,"kode_terminal":154,"pin":18,"date_time":"2022-02-09 12:00:24","ver":1,"status":0},{"id":1257,"kode_terminal":154,"pin":15,"date_time":"2022-02-09 12:01:07","ver":1,"status":0},{"id":1258,"kode_terminal":154,"pin":22,"date_time":"2022-02-09 12:07:08","ver":1,"status":0},{"id":1259,"kode_terminal":154,"pin":17,"date_time":"2022-02-09 12:07:36","ver":1,"status":0},{"id":1260,"kode_terminal":154,"pin":4,"date_time":"2022-02-09 12:23:01","ver":1,"status":0},{"id":1261,"kode_terminal":154,"pin":19,"date_time":"2022-02-09 12:25:34","ver":1,"status":0},{"id":1262,"kode_terminal":154,"pin":2,"date_time":"2022-02-09 12:47:39","ver":1,"status":0},{"id":1263,"kode_terminal":154,"pin":14,"date_time":"2022-02-09 13:02:28","ver":1,"status":0},{"id":1264,"kode_terminal":154,"pin":18,"date_time":"2022-02-09 16:00:11","ver":1,"status":1},{"id":1265,"kode_terminal":154,"pin":17,"date_time":"2022-02-09 16:00:32","ver":1,"status":1},{"id":1266,"kode_terminal":154,"pin":13,"date_time":"2022-02-09 16:01:10","ver":1,"status":1},{"id":1267,"kode_terminal":154,"pin":15,"date_time":"2022-02-09 16:02:02","ver":1,"status":1},{"id":1268,"kode_terminal":154,"pin":22,"date_time":"2022-02-09 16:02:16","ver":1,"status":1},{"id":1269,"kode_terminal":154,"pin":4,"date_time":"2022-02-09 16:04:01","ver":1,"status":1},{"id":1270,"kode_terminal":154,"pin":17,"date_time":"2022-02-09 16:06:52","ver":1,"status":1},{"id":1271,"kode_terminal":154,"pin":17,"date_time":"2022-02-09 16:14:16","ver":1,"status":1},{"id":1272,"kode_terminal":154,"pin":2,"date_time":"2022-02-09 16:32:52","ver":1,"status":1},{"id":1273,"kode_terminal":154,"pin":14,"date_time":"2022-02-09 16:37:11","ver":1,"status":1},{"id":1274,"kode_terminal":154,"pin":19,"date_time":"2022-02-09 16:40:48","ver":1,"status":1},{"id":1275,"kode_terminal":154,"pin":4,"date_time":"2022-02-10 07:00:15","ver":1,"status":0},{"id":1276,"kode_terminal":154,"pin":18,"date_time":"2022-02-10 07:00:36","ver":1,"status":0},{"id":1277,"kode_terminal":154,"pin":22,"date_time":"2022-02-10 07:14:03","ver":1,"status":0},{"id":1278,"kode_terminal":154,"pin":19,"date_time":"2022-02-10 07:19:52","ver":1,"status":0},{"id":1279,"kode_terminal":154,"pin":14,"date_time":"2022-02-10 07:34:48","ver":1,"status":0},{"id":1280,"kode_terminal":154,"pin":17,"date_time":"2022-02-10 07:50:03","ver":1,"status":0},{"id":1281,"kode_terminal":154,"pin":17,"date_time":"2022-02-10 07:51:45","ver":1,"status":0},{"id":1282,"kode_terminal":154,"pin":20,"date_time":"2022-02-10 09:19:07","ver":1,"status":0},{"id":1283,"kode_terminal":154,"pin":13,"date_time":"2022-02-10 09:28:43","ver":1,"status":0},{"id":1284,"kode_terminal":154,"pin":15,"date_time":"2022-02-10 10:03:00","ver":1,"status":0},{"id":1285,"kode_terminal":154,"pin":2,"date_time":"2022-02-10 11:28:25","ver":1,"status":0},{"id":1286,"kode_terminal":154,"pin":18,"date_time":"2022-02-10 12:00:20","ver":1,"status":0},{"id":1287,"kode_terminal":154,"pin":13,"date_time":"2022-02-10 12:00:26","ver":1,"status":0},{"id":1288,"kode_terminal":154,"pin":15,"date_time":"2022-02-10 12:02:57","ver":1,"status":0},{"id":1289,"kode_terminal":154,"pin":22,"date_time":"2022-02-10 12:09:48","ver":1,"status":0},{"id":1290,"kode_terminal":154,"pin":19,"date_time":"2022-02-10 12:16:59","ver":1,"status":0},{"id":1291,"kode_terminal":154,"pin":2,"date_time":"2022-02-10 12:20:10","ver":1,"status":0},{"id":1292,"kode_terminal":154,"pin":4,"date_time":"2022-02-10 12:24:00","ver":1,"status":0},{"id":1293,"kode_terminal":154,"pin":17,"date_time":"2022-02-10 12:29:44","ver":1,"status":0},{"id":1294,"kode_terminal":154,"pin":17,"date_time":"2022-02-10 12:44:11","ver":1,"status":0},{"id":1295,"kode_terminal":154,"pin":17,"date_time":"2022-02-10 16:00:26","ver":1,"status":0},{"id":1296,"kode_terminal":154,"pin":18,"date_time":"2022-02-10 16:00:38","ver":1,"status":0},{"id":1297,"kode_terminal":154,"pin":4,"date_time":"2022-02-10 16:01:31","ver":1,"status":0},{"id":1298,"kode_terminal":154,"pin":22,"date_time":"2022-02-10 16:01:49","ver":1,"status":0},{"id":1299,"kode_terminal":154,"pin":15,"date_time":"2022-02-10 16:06:51","ver":1,"status":0},{"id":1300,"kode_terminal":154,"pin":19,"date_time":"2022-02-10 16:09:42","ver":1,"status":0},{"id":1301,"kode_terminal":154,"pin":13,"date_time":"2022-02-10 16:18:19","ver":1,"status":0},{"id":1302,"kode_terminal":154,"pin":2,"date_time":"2022-02-10 16:37:28","ver":1,"status":1},{"id":1303,"kode_terminal":154,"pin":18,"date_time":"2022-02-11 07:00:09","ver":1,"status":0},{"id":1304,"kode_terminal":154,"pin":4,"date_time":"2022-02-11 07:01:03","ver":1,"status":0},{"id":1305,"kode_terminal":154,"pin":14,"date_time":"2022-02-11 07:05:39","ver":1,"status":0},{"id":1306,"kode_terminal":154,"pin":19,"date_time":"2022-02-11 07:31:57","ver":1,"status":0},{"id":1307,"kode_terminal":154,"pin":17,"date_time":"2022-02-11 07:49:57","ver":1,"status":0},{"id":1308,"kode_terminal":154,"pin":15,"date_time":"2022-02-11 08:14:47","ver":1,"status":0},{"id":1309,"kode_terminal":154,"pin":2,"date_time":"2022-02-11 10:58:29","ver":1,"status":0},{"id":1310,"kode_terminal":154,"pin":4,"date_time":"2022-02-11 12:01:19","ver":1,"status":0},{"id":1311,"kode_terminal":154,"pin":18,"date_time":"2022-02-11 12:01:44","ver":1,"status":0},{"id":1312,"kode_terminal":154,"pin":2,"date_time":"2022-02-11 12:14:02","ver":1,"status":0},{"id":1313,"kode_terminal":154,"pin":17,"date_time":"2022-02-11 12:16:13","ver":1,"status":0},{"id":1314,"kode_terminal":154,"pin":17,"date_time":"2022-02-11 12:17:54","ver":1,"status":0},{"id":1315,"kode_terminal":154,"pin":15,"date_time":"2022-02-11 12:56:18","ver":1,"status":0},{"id":1316,"kode_terminal":154,"pin":17,"date_time":"2022-02-11 16:30:29","ver":1,"status":0},{"id":1317,"kode_terminal":154,"pin":18,"date_time":"2022-02-11 16:30:56","ver":1,"status":1},{"id":1318,"kode_terminal":154,"pin":15,"date_time":"2022-02-11 16:31:28","ver":1,"status":1},{"id":1319,"kode_terminal":154,"pin":4,"date_time":"2022-02-11 16:32:24","ver":1,"status":1},{"id":1320,"kode_terminal":154,"pin":14,"date_time":"2022-02-11 16:46:21","ver":1,"status":1},{"id":1321,"kode_terminal":154,"pin":2,"date_time":"2022-02-11 16:57:12","ver":1,"status":1},{"id":1322,"kode_terminal":154,"pin":4,"date_time":"2022-02-14 07:00:03","ver":1,"status":0},{"id":1323,"kode_terminal":154,"pin":18,"date_time":"2022-02-14 07:01:40","ver":1,"status":0},{"id":1324,"kode_terminal":154,"pin":22,"date_time":"2022-02-14 07:18:42","ver":1,"status":0},{"id":1325,"kode_terminal":154,"pin":14,"date_time":"2022-02-14 07:27:15","ver":1,"status":0},{"id":1326,"kode_terminal":154,"pin":15,"date_time":"2022-02-14 07:41:14","ver":1,"status":0},{"id":1327,"kode_terminal":154,"pin":17,"date_time":"2022-02-14 07:56:26","ver":1,"status":0},{"id":1328,"kode_terminal":154,"pin":13,"date_time":"2022-02-14 07:56:47","ver":1,"status":0},{"id":1329,"kode_terminal":154,"pin":20,"date_time":"2022-02-14 09:21:15","ver":1,"status":0},{"id":1330,"kode_terminal":154,"pin":2,"date_time":"2022-02-14 11:11:31","ver":1,"status":0},{"id":1331,"kode_terminal":154,"pin":18,"date_time":"2022-02-14 12:01:36","ver":1,"status":0},{"id":1332,"kode_terminal":154,"pin":17,"date_time":"2022-02-14 12:01:48","ver":1,"status":0},{"id":1333,"kode_terminal":154,"pin":2,"date_time":"2022-02-14 12:03:54","ver":1,"status":0},{"id":1334,"kode_terminal":154,"pin":13,"date_time":"2022-02-14 12:07:38","ver":1,"status":0},{"id":1335,"kode_terminal":154,"pin":22,"date_time":"2022-02-14 12:14:43","ver":1,"status":0},{"id":1336,"kode_terminal":154,"pin":4,"date_time":"2022-02-14 12:24:25","ver":1,"status":0},{"id":1337,"kode_terminal":154,"pin":19,"date_time":"2022-02-14 12:33:31","ver":1,"status":0},{"id":1338,"kode_terminal":154,"pin":14,"date_time":"2022-02-14 12:41:18","ver":1,"status":0},{"id":1339,"kode_terminal":154,"pin":18,"date_time":"2022-02-14 16:00:27","ver":1,"status":1},{"id":1340,"kode_terminal":154,"pin":17,"date_time":"2022-02-14 16:00:54","ver":1,"status":1},{"id":1341,"kode_terminal":154,"pin":13,"date_time":"2022-02-14 16:03:22","ver":1,"status":1},{"id":1342,"kode_terminal":154,"pin":4,"date_time":"2022-02-14 16:03:33","ver":1,"status":1},{"id":1343,"kode_terminal":154,"pin":19,"date_time":"2022-02-14 16:07:58","ver":1,"status":1},{"id":1344,"kode_terminal":154,"pin":15,"date_time":"2022-02-14 16:35:13","ver":1,"status":1},{"id":1345,"kode_terminal":154,"pin":22,"date_time":"2022-02-14 16:48:24","ver":1,"status":1},{"id":1346,"kode_terminal":154,"pin":14,"date_time":"2022-02-14 17:04:33","ver":1,"status":1},{"id":1347,"kode_terminal":154,"pin":2,"date_time":"2022-02-14 18:09:28","ver":1,"status":1},{"id":1348,"kode_terminal":154,"pin":4,"date_time":"2022-02-15 07:00:03","ver":1,"status":0},{"id":1349,"kode_terminal":154,"pin":22,"date_time":"2022-02-15 07:37:33","ver":1,"status":0},{"id":1350,"kode_terminal":154,"pin":14,"date_time":"2022-02-15 07:40:38","ver":1,"status":0},{"id":1351,"kode_terminal":154,"pin":18,"date_time":"2022-02-15 07:56:53","ver":1,"status":0},{"id":1352,"kode_terminal":154,"pin":17,"date_time":"2022-02-15 07:57:04","ver":1,"status":0},{"id":1353,"kode_terminal":154,"pin":19,"date_time":"2022-02-15 08:23:37","ver":1,"status":0},{"id":1354,"kode_terminal":154,"pin":20,"date_time":"2022-02-15 08:56:45","ver":1,"status":0},{"id":1355,"kode_terminal":154,"pin":13,"date_time":"2022-02-15 09:09:51","ver":1,"status":0},{"id":1356,"kode_terminal":154,"pin":15,"date_time":"2022-02-15 10:05:30","ver":1,"status":0},{"id":1357,"kode_terminal":154,"pin":2,"date_time":"2022-02-15 10:28:31","ver":1,"status":0},{"id":1358,"kode_terminal":154,"pin":18,"date_time":"2022-02-15 12:00:30","ver":1,"status":0},{"id":1359,"kode_terminal":154,"pin":13,"date_time":"2022-02-15 12:01:32","ver":1,"status":0},{"id":1360,"kode_terminal":154,"pin":15,"date_time":"2022-02-15 12:09:05","ver":1,"status":0},{"id":1361,"kode_terminal":154,"pin":4,"date_time":"2022-02-15 12:13:14","ver":1,"status":0},{"id":1362,"kode_terminal":154,"pin":19,"date_time":"2022-02-15 12:15:32","ver":1,"status":0},{"id":1363,"kode_terminal":154,"pin":2,"date_time":"2022-02-15 12:16:21","ver":1,"status":0},{"id":1364,"kode_terminal":154,"pin":17,"date_time":"2022-02-15 12:20:15","ver":1,"status":0},{"id":1365,"kode_terminal":154,"pin":17,"date_time":"2022-02-15 12:24:58","ver":1,"status":0},{"id":1366,"kode_terminal":154,"pin":14,"date_time":"2022-02-15 12:25:47","ver":1,"status":0},{"id":1367,"kode_terminal":154,"pin":22,"date_time":"2022-02-15 12:26:25","ver":1,"status":0},{"id":1368,"kode_terminal":154,"pin":20,"date_time":"2022-02-15 12:48:12","ver":1,"status":0},{"id":1369,"kode_terminal":154,"pin":14,"date_time":"2022-02-15 15:31:15","ver":1,"status":1},{"id":1370,"kode_terminal":154,"pin":18,"date_time":"2022-02-15 16:00:28","ver":1,"status":1},{"id":1371,"kode_terminal":154,"pin":17,"date_time":"2022-02-15 16:01:06","ver":1,"status":1},{"id":1372,"kode_terminal":154,"pin":15,"date_time":"2022-02-15 16:02:06","ver":1,"status":1},{"id":1373,"kode_terminal":154,"pin":4,"date_time":"2022-02-15 16:03:26","ver":1,"status":1},{"id":1374,"kode_terminal":154,"pin":19,"date_time":"2022-02-15 16:03:58","ver":1,"status":1},{"id":1375,"kode_terminal":154,"pin":2,"date_time":"2022-02-15 16:20:23","ver":1,"status":1},{"id":1376,"kode_terminal":154,"pin":14,"date_time":"2022-02-15 16:26:08","ver":1,"status":1},{"id":1377,"kode_terminal":154,"pin":13,"date_time":"2022-02-15 16:36:58","ver":1,"status":1},{"id":1378,"kode_terminal":154,"pin":22,"date_time":"2022-02-15 16:37:09","ver":1,"status":1},{"id":1379,"kode_terminal":154,"pin":22,"date_time":"2022-02-16 07:02:09","ver":1,"status":0},{"id":1380,"kode_terminal":154,"pin":4,"date_time":"2022-02-16 07:27:58","ver":1,"status":0},{"id":1381,"kode_terminal":154,"pin":18,"date_time":"2022-02-16 07:33:42","ver":1,"status":0},{"id":1382,"kode_terminal":154,"pin":14,"date_time":"2022-02-16 07:34:44","ver":1,"status":0},{"id":1383,"kode_terminal":154,"pin":17,"date_time":"2022-02-16 07:43:22","ver":1,"status":0},{"id":1384,"kode_terminal":154,"pin":19,"date_time":"2022-02-16 07:53:33","ver":1,"status":0},{"id":1385,"kode_terminal":154,"pin":15,"date_time":"2022-02-16 11:02:00","ver":1,"status":0},{"id":1386,"kode_terminal":154,"pin":18,"date_time":"2022-02-16 12:00:16","ver":1,"status":0},{"id":1387,"kode_terminal":154,"pin":17,"date_time":"2022-02-16 12:00:56","ver":1,"status":0},{"id":1388,"kode_terminal":154,"pin":15,"date_time":"2022-02-16 12:02:04","ver":1,"status":0},{"id":1389,"kode_terminal":154,"pin":17,"date_time":"2022-02-16 12:15:34","ver":1,"status":0},{"id":1390,"kode_terminal":154,"pin":14,"date_time":"2022-02-16 12:16:05","ver":1,"status":0},{"id":1391,"kode_terminal":154,"pin":22,"date_time":"2022-02-16 12:19:51","ver":1,"status":0},{"id":1392,"kode_terminal":154,"pin":4,"date_time":"2022-02-16 12:46:43","ver":1,"status":0},{"id":1393,"kode_terminal":154,"pin":17,"date_time":"2022-02-16 16:00:11","ver":1,"status":0},{"id":1394,"kode_terminal":154,"pin":2,"date_time":"2022-02-16 16:00:23","ver":1,"status":0},{"id":1395,"kode_terminal":154,"pin":14,"date_time":"2022-02-16 16:00:31","ver":1,"status":0},{"id":1396,"kode_terminal":154,"pin":18,"date_time":"2022-02-16 16:00:40","ver":1,"status":1},{"id":1397,"kode_terminal":154,"pin":15,"date_time":"2022-02-16 16:01:05","ver":1,"status":1},{"id":1398,"kode_terminal":154,"pin":22,"date_time":"2022-02-16 16:37:29","ver":1,"status":1},{"id":1399,"kode_terminal":154,"pin":19,"date_time":"2022-02-16 16:37:52","ver":1,"status":1},{"id":1400,"kode_terminal":154,"pin":4,"date_time":"2022-02-17 07:01:55","ver":1,"status":0},{"id":1401,"kode_terminal":154,"pin":17,"date_time":"2022-02-17 07:10:17","ver":1,"status":0},{"id":1402,"kode_terminal":154,"pin":18,"date_time":"2022-02-17 07:14:53","ver":1,"status":0},{"id":1403,"kode_terminal":154,"pin":14,"date_time":"2022-02-17 07:26:20","ver":1,"status":0},{"id":1404,"kode_terminal":154,"pin":22,"date_time":"2022-02-17 07:40:01","ver":1,"status":0},{"id":1405,"kode_terminal":154,"pin":19,"date_time":"2022-02-17 07:54:06","ver":1,"status":0},{"id":1406,"kode_terminal":154,"pin":2,"date_time":"2022-02-17 09:02:57","ver":1,"status":0},{"id":1407,"kode_terminal":154,"pin":13,"date_time":"2022-02-17 10:51:35","ver":1,"status":0},{"id":1408,"kode_terminal":154,"pin":13,"date_time":"2022-02-17 12:00:23","ver":1,"status":0},{"id":1409,"kode_terminal":154,"pin":18,"date_time":"2022-02-17 12:00:36","ver":1,"status":0},{"id":1410,"kode_terminal":154,"pin":22,"date_time":"2022-02-17 12:03:35","ver":1,"status":0},{"id":1411,"kode_terminal":154,"pin":17,"date_time":"2022-02-17 12:29:15","ver":1,"status":0},{"id":1412,"kode_terminal":154,"pin":2,"date_time":"2022-02-17 12:30:29","ver":1,"status":0},{"id":1413,"kode_terminal":154,"pin":14,"date_time":"2022-02-17 12:50:43","ver":1,"status":0},{"id":1414,"kode_terminal":154,"pin":19,"date_time":"2022-02-17 12:59:00","ver":1,"status":0},{"id":1415,"kode_terminal":154,"pin":4,"date_time":"2022-02-17 13:16:26","ver":1,"status":0},{"id":1416,"kode_terminal":154,"pin":17,"date_time":"2022-02-17 16:00:12","ver":1,"status":1},{"id":1417,"kode_terminal":154,"pin":18,"date_time":"2022-02-17 16:00:30","ver":1,"status":1},{"id":1418,"kode_terminal":154,"pin":19,"date_time":"2022-02-17 16:01:00","ver":1,"status":1},{"id":1419,"kode_terminal":154,"pin":4,"date_time":"2022-02-17 16:31:49","ver":1,"status":1},{"id":1420,"kode_terminal":154,"pin":22,"date_time":"2022-02-17 16:32:18","ver":1,"status":1},{"id":1421,"kode_terminal":154,"pin":14,"date_time":"2022-02-17 16:41:10","ver":1,"status":1},{"id":1422,"kode_terminal":154,"pin":13,"date_time":"2022-02-17 16:49:05","ver":1,"status":1},{"id":1423,"kode_terminal":154,"pin":2,"date_time":"2022-02-17 17:17:13","ver":1,"status":1},{"id":1424,"kode_terminal":154,"pin":4,"date_time":"2022-02-18 07:00:03","ver":1,"status":0},{"id":1425,"kode_terminal":154,"pin":18,"date_time":"2022-02-18 07:13:37","ver":1,"status":0},{"id":1426,"kode_terminal":154,"pin":17,"date_time":"2022-02-18 07:13:56","ver":1,"status":0},{"id":1427,"kode_terminal":154,"pin":13,"date_time":"2022-02-18 07:15:01","ver":1,"status":0},{"id":1428,"kode_terminal":154,"pin":22,"date_time":"2022-02-18 07:18:45","ver":1,"status":0},{"id":1429,"kode_terminal":154,"pin":14,"date_time":"2022-02-18 08:20:35","ver":1,"status":0},{"id":1430,"kode_terminal":154,"pin":19,"date_time":"2022-02-18 08:39:58","ver":1,"status":0},{"id":1431,"kode_terminal":154,"pin":15,"date_time":"2022-02-18 10:08:50","ver":1,"status":0},{"id":1432,"kode_terminal":154,"pin":2,"date_time":"2022-02-18 11:09:37","ver":1,"status":0},{"id":1433,"kode_terminal":154,"pin":2,"date_time":"2022-02-18 12:00:19","ver":1,"status":0},{"id":1434,"kode_terminal":154,"pin":15,"date_time":"2022-02-18 12:03:38","ver":1,"status":0},{"id":1435,"kode_terminal":154,"pin":18,"date_time":"2022-02-18 12:05:01","ver":1,"status":0},{"id":1436,"kode_terminal":154,"pin":22,"date_time":"2022-02-18 12:11:57","ver":1,"status":0},{"id":1437,"kode_terminal":154,"pin":14,"date_time":"2022-02-18 12:17:50","ver":1,"status":0},{"id":1438,"kode_terminal":154,"pin":17,"date_time":"2022-02-18 12:19:52","ver":1,"status":0},{"id":1439,"kode_terminal":154,"pin":17,"date_time":"2022-02-18 12:21:36","ver":1,"status":0},{"id":1440,"kode_terminal":154,"pin":19,"date_time":"2022-02-18 12:42:48","ver":1,"status":0},{"id":1441,"kode_terminal":154,"pin":13,"date_time":"2022-02-18 12:55:52","ver":1,"status":0},{"id":1442,"kode_terminal":154,"pin":4,"date_time":"2022-02-18 13:00:00","ver":1,"status":0},{"id":1443,"kode_terminal":154,"pin":15,"date_time":"2022-02-18 16:30:19","ver":1,"status":0},{"id":1444,"kode_terminal":154,"pin":18,"date_time":"2022-02-18 16:31:32","ver":1,"status":1},{"id":1445,"kode_terminal":154,"pin":4,"date_time":"2022-02-18 16:32:06","ver":1,"status":1},{"id":1446,"kode_terminal":154,"pin":17,"date_time":"2022-02-18 16:32:21","ver":1,"status":1},{"id":1447,"kode_terminal":154,"pin":14,"date_time":"2022-02-18 16:40:55","ver":1,"status":1},{"id":1448,"kode_terminal":154,"pin":22,"date_time":"2022-02-18 16:49:08","ver":1,"status":1},{"id":1449,"kode_terminal":154,"pin":4,"date_time":"2022-02-21 07:00:03","ver":1,"status":0},{"id":1450,"kode_terminal":154,"pin":18,"date_time":"2022-02-21 07:00:23","ver":1,"status":0},{"id":1451,"kode_terminal":154,"pin":19,"date_time":"2022-02-21 07:14:43","ver":1,"status":0},{"id":1452,"kode_terminal":154,"pin":22,"date_time":"2022-02-21 07:33:20","ver":1,"status":0},{"id":1453,"kode_terminal":154,"pin":14,"date_time":"2022-02-21 07:34:06","ver":1,"status":0},{"id":1454,"kode_terminal":154,"pin":17,"date_time":"2022-02-21 07:49:49","ver":1,"status":0},{"id":1455,"kode_terminal":154,"pin":2,"date_time":"2022-02-21 07:59:20","ver":1,"status":0},{"id":1456,"kode_terminal":154,"pin":15,"date_time":"2022-02-21 09:18:57","ver":1,"status":0},{"id":1457,"kode_terminal":154,"pin":18,"date_time":"2022-02-21 12:00:33","ver":1,"status":0},{"id":1458,"kode_terminal":154,"pin":17,"date_time":"2022-02-21 12:01:01","ver":1,"status":0},{"id":1459,"kode_terminal":154,"pin":4,"date_time":"2022-02-21 12:01:29","ver":1,"status":0},{"id":1460,"kode_terminal":154,"pin":15,"date_time":"2022-02-21 12:04:08","ver":1,"status":0},{"id":1461,"kode_terminal":154,"pin":22,"date_time":"2022-02-21 12:16:56","ver":1,"status":0},{"id":1462,"kode_terminal":154,"pin":2,"date_time":"2022-02-21 12:30:44","ver":1,"status":0},{"id":1463,"kode_terminal":154,"pin":14,"date_time":"2022-02-21 12:33:54","ver":1,"status":0},{"id":1464,"kode_terminal":154,"pin":15,"date_time":"2022-02-21 16:00:34","ver":1,"status":1},{"id":1465,"kode_terminal":154,"pin":18,"date_time":"2022-02-21 16:01:06","ver":1,"status":1},{"id":1466,"kode_terminal":154,"pin":4,"date_time":"2022-02-21 16:29:25","ver":1,"status":1},{"id":1467,"kode_terminal":154,"pin":17,"date_time":"2022-02-21 16:43:42","ver":1,"status":1},{"id":1468,"kode_terminal":154,"pin":19,"date_time":"2022-02-21 16:44:12","ver":1,"status":1},{"id":1469,"kode_terminal":154,"pin":22,"date_time":"2022-02-21 17:40:19","ver":1,"status":1},{"id":1470,"kode_terminal":154,"pin":2,"date_time":"2022-02-21 17:54:05","ver":1,"status":1},{"id":1471,"kode_terminal":154,"pin":4,"date_time":"2022-02-22 07:13:43","ver":1,"status":0},{"id":1472,"kode_terminal":154,"pin":14,"date_time":"2022-02-22 07:15:05","ver":1,"status":0},{"id":1473,"kode_terminal":154,"pin":17,"date_time":"2022-02-22 07:19:06","ver":1,"status":0},{"id":1474,"kode_terminal":154,"pin":19,"date_time":"2022-02-22 07:46:06","ver":1,"status":0},{"id":1475,"kode_terminal":154,"pin":18,"date_time":"2022-02-22 08:20:08","ver":1,"status":0},{"id":1476,"kode_terminal":154,"pin":2,"date_time":"2022-02-22 09:53:55","ver":1,"status":0},{"id":1477,"kode_terminal":154,"pin":22,"date_time":"2022-02-22 11:45:34","ver":1,"status":0},{"id":1478,"kode_terminal":154,"pin":18,"date_time":"2022-02-22 12:00:57","ver":1,"status":0},{"id":1479,"kode_terminal":154,"pin":17,"date_time":"2022-02-22 12:01:17","ver":1,"status":0},{"id":1480,"kode_terminal":154,"pin":14,"date_time":"2022-02-22 12:01:31","ver":1,"status":0},{"id":1481,"kode_terminal":154,"pin":22,"date_time":"2022-02-22 12:04:35","ver":1,"status":0},{"id":1482,"kode_terminal":154,"pin":17,"date_time":"2022-02-22 12:04:57","ver":1,"status":0},{"id":1483,"kode_terminal":154,"pin":2,"date_time":"2022-02-22 12:07:05","ver":1,"status":0},{"id":1484,"kode_terminal":154,"pin":4,"date_time":"2022-02-22 12:17:16","ver":1,"status":0},{"id":1485,"kode_terminal":154,"pin":19,"date_time":"2022-02-22 12:17:32","ver":1,"status":0},{"id":1486,"kode_terminal":154,"pin":18,"date_time":"2022-02-22 16:00:45","ver":1,"status":1},{"id":1487,"kode_terminal":154,"pin":4,"date_time":"2022-02-22 16:03:11","ver":1,"status":1},{"id":1488,"kode_terminal":154,"pin":17,"date_time":"2022-02-22 16:03:24","ver":1,"status":1},{"id":1489,"kode_terminal":154,"pin":2,"date_time":"2022-02-22 16:07:25","ver":1,"status":1},{"id":1490,"kode_terminal":154,"pin":19,"date_time":"2022-02-22 16:12:08","ver":1,"status":1},{"id":1491,"kode_terminal":154,"pin":22,"date_time":"2022-02-22 18:15:11","ver":1,"status":1},{"id":1492,"kode_terminal":154,"pin":14,"date_time":"2022-02-22 18:15:22","ver":1,"status":1},{"id":1493,"kode_terminal":154,"pin":18,"date_time":"2022-02-23 07:01:02","ver":1,"status":0},{"id":1494,"kode_terminal":154,"pin":4,"date_time":"2022-02-23 07:02:06","ver":1,"status":0},{"id":1495,"kode_terminal":154,"pin":14,"date_time":"2022-02-23 07:13:33","ver":1,"status":0},{"id":1496,"kode_terminal":154,"pin":22,"date_time":"2022-02-23 07:13:49","ver":1,"status":0},{"id":1497,"kode_terminal":154,"pin":17,"date_time":"2022-02-23 07:26:10","ver":1,"status":0},{"id":1498,"kode_terminal":154,"pin":15,"date_time":"2022-02-23 07:26:47","ver":1,"status":0},{"id":1499,"kode_terminal":154,"pin":20,"date_time":"2022-02-23 08:00:41","ver":1,"status":0},{"id":1500,"kode_terminal":154,"pin":19,"date_time":"2022-02-23 08:12:47","ver":1,"status":0},{"id":1501,"kode_terminal":154,"pin":2,"date_time":"2022-02-23 10:01:59","ver":1,"status":0},{"id":1502,"kode_terminal":154,"pin":13,"date_time":"2022-02-23 10:12:19","ver":1,"status":0},{"id":1503,"kode_terminal":154,"pin":17,"date_time":"2022-02-23 12:00:23","ver":1,"status":0},{"id":1504,"kode_terminal":154,"pin":4,"date_time":"2022-02-23 12:03:16","ver":1,"status":0},{"id":1505,"kode_terminal":154,"pin":13,"date_time":"2022-02-23 12:04:03","ver":1,"status":0},{"id":1506,"kode_terminal":154,"pin":18,"date_time":"2022-02-23 12:04:28","ver":1,"status":0},{"id":1507,"kode_terminal":154,"pin":22,"date_time":"2022-02-23 12:05:29","ver":1,"status":0},{"id":1508,"kode_terminal":154,"pin":14,"date_time":"2022-02-23 12:20:28","ver":1,"status":0},{"id":1509,"kode_terminal":154,"pin":19,"date_time":"2022-02-23 12:20:38","ver":1,"status":0},{"id":1510,"kode_terminal":154,"pin":2,"date_time":"2022-02-23 12:21:45","ver":1,"status":0},{"id":1511,"kode_terminal":154,"pin":15,"date_time":"2022-02-23 12:30:53","ver":1,"status":0},{"id":1512,"kode_terminal":154,"pin":20,"date_time":"2022-02-23 12:55:16","ver":1,"status":0},{"id":1513,"kode_terminal":154,"pin":17,"date_time":"2022-02-23 16:01:31","ver":1,"status":0},{"id":1514,"kode_terminal":154,"pin":4,"date_time":"2022-02-23 16:01:44","ver":1,"status":1},{"id":1515,"kode_terminal":154,"pin":18,"date_time":"2022-02-23 16:03:11","ver":1,"status":1},{"id":1516,"kode_terminal":154,"pin":19,"date_time":"2022-02-23 16:12:55","ver":1,"status":1},{"id":1517,"kode_terminal":154,"pin":2,"date_time":"2022-02-23 16:48:39","ver":1,"status":1},{"id":1518,"kode_terminal":154,"pin":14,"date_time":"2022-02-23 16:51:09","ver":1,"status":1},{"id":1519,"kode_terminal":154,"pin":15,"date_time":"2022-02-23 16:52:23","ver":1,"status":1},{"id":1520,"kode_terminal":154,"pin":22,"date_time":"2022-02-23 18:37:02","ver":1,"status":1},{"id":1521,"kode_terminal":154,"pin":4,"date_time":"2022-02-24 07:00:51","ver":1,"status":0},{"id":1522,"kode_terminal":154,"pin":14,"date_time":"2022-02-24 07:03:54","ver":1,"status":0},{"id":1523,"kode_terminal":154,"pin":19,"date_time":"2022-02-24 07:07:46","ver":1,"status":0},{"id":1524,"kode_terminal":154,"pin":17,"date_time":"2022-02-24 07:17:28","ver":1,"status":0},{"id":1525,"kode_terminal":154,"pin":18,"date_time":"2022-02-24 07:19:56","ver":1,"status":0},{"id":1526,"kode_terminal":154,"pin":22,"date_time":"2022-02-24 11:05:32","ver":1,"status":0},{"id":1527,"kode_terminal":154,"pin":18,"date_time":"2022-02-24 12:00:50","ver":1,"status":0},{"id":1528,"kode_terminal":154,"pin":14,"date_time":"2022-02-24 12:01:08","ver":1,"status":0},{"id":1529,"kode_terminal":154,"pin":15,"date_time":"2022-02-24 12:08:12","ver":1,"status":0},{"id":1530,"kode_terminal":154,"pin":4,"date_time":"2022-02-24 12:29:33","ver":1,"status":0},{"id":1531,"kode_terminal":154,"pin":19,"date_time":"2022-02-24 12:31:00","ver":1,"status":0},{"id":1532,"kode_terminal":154,"pin":22,"date_time":"2022-02-24 12:31:29","ver":1,"status":0},{"id":1533,"kode_terminal":154,"pin":17,"date_time":"2022-02-24 12:50:49","ver":1,"status":0},{"id":1534,"kode_terminal":154,"pin":18,"date_time":"2022-02-24 16:00:43","ver":1,"status":1},{"id":1535,"kode_terminal":154,"pin":4,"date_time":"2022-02-24 16:00:56","ver":1,"status":1},{"id":1536,"kode_terminal":154,"pin":17,"date_time":"2022-02-24 16:01:19","ver":1,"status":1},{"id":1537,"kode_terminal":154,"pin":19,"date_time":"2022-02-24 16:12:26","ver":1,"status":1},{"id":1538,"kode_terminal":154,"pin":15,"date_time":"2022-02-24 16:28:40","ver":1,"status":1},{"id":1539,"kode_terminal":154,"pin":22,"date_time":"2022-02-24 17:07:11","ver":1,"status":1},{"id":1540,"kode_terminal":154,"pin":14,"date_time":"2022-02-24 18:02:31","ver":1,"status":1},{"id":1541,"kode_terminal":154,"pin":18,"date_time":"2022-02-25 07:00:35","ver":1,"status":0},{"id":1542,"kode_terminal":154,"pin":4,"date_time":"2022-02-25 07:00:53","ver":1,"status":0},{"id":1543,"kode_terminal":154,"pin":19,"date_time":"2022-02-25 07:01:44","ver":1,"status":0},{"id":1544,"kode_terminal":154,"pin":17,"date_time":"2022-02-25 07:11:58","ver":1,"status":0},{"id":1545,"kode_terminal":154,"pin":22,"date_time":"2022-02-25 07:14:27","ver":1,"status":0},{"id":1546,"kode_terminal":154,"pin":14,"date_time":"2022-02-25 07:20:45","ver":1,"status":0},{"id":1547,"kode_terminal":154,"pin":15,"date_time":"2022-02-25 08:34:50","ver":1,"status":0},{"id":1548,"kode_terminal":154,"pin":2,"date_time":"2022-02-25 09:46:22","ver":1,"status":0},{"id":1549,"kode_terminal":154,"pin":2,"date_time":"2022-02-25 12:09:06","ver":1,"status":0},{"id":1550,"kode_terminal":154,"pin":18,"date_time":"2022-02-25 12:10:52","ver":1,"status":0},{"id":1551,"kode_terminal":154,"pin":19,"date_time":"2022-02-25 12:18:10","ver":1,"status":0},{"id":1552,"kode_terminal":154,"pin":14,"date_time":"2022-02-25 12:18:48","ver":1,"status":0},{"id":1553,"kode_terminal":154,"pin":4,"date_time":"2022-02-25 12:25:48","ver":1,"status":0},{"id":1554,"kode_terminal":154,"pin":17,"date_time":"2022-02-25 12:27:35","ver":1,"status":0},{"id":1555,"kode_terminal":154,"pin":22,"date_time":"2022-02-25 12:32:39","ver":1,"status":0},{"id":1556,"kode_terminal":154,"pin":15,"date_time":"2022-02-25 12:47:07","ver":1,"status":0},{"id":1557,"kode_terminal":154,"pin":17,"date_time":"2022-02-25 12:50:57","ver":1,"status":0},{"id":1558,"kode_terminal":154,"pin":4,"date_time":"2022-02-25 16:19:40","ver":1,"status":0},{"id":1559,"kode_terminal":154,"pin":18,"date_time":"2022-02-25 16:30:26","ver":1,"status":1},{"id":1560,"kode_terminal":154,"pin":4,"date_time":"2022-02-25 16:30:44","ver":1,"status":1},{"id":1561,"kode_terminal":154,"pin":17,"date_time":"2022-02-25 16:31:14","ver":1,"status":1},{"id":1562,"kode_terminal":154,"pin":19,"date_time":"2022-02-25 16:47:56","ver":1,"status":1},{"id":1563,"kode_terminal":154,"pin":15,"date_time":"2022-02-25 16:58:54","ver":1,"status":1},{"id":1564,"kode_terminal":154,"pin":22,"date_time":"2022-02-25 17:04:39","ver":1,"status":1},{"id":1565,"kode_terminal":154,"pin":2,"date_time":"2022-02-25 17:26:43","ver":1,"status":1},{"id":1566,"kode_terminal":154,"pin":14,"date_time":"2022-02-25 17:52:31","ver":1,"status":1}]